[
    {
        "id": "32891548788",
        "type": "WatchEvent",
        "actor": {
            "id": 532096,
            "login": "Martouf",
            "display_login": "Martouf",
            "gravatar_id": "",
            "url": "https://api.github.com/users/Martouf",
            "avatar_url": "https://avatars.githubusercontent.com/u/532096?"
        },
        "repo": {
            "id": 124678204,
            "name": "aircrack-ng/aircrack-ng",
            "url": "https://api.github.com/repos/aircrack-ng/aircrack-ng"
        },
        "payload": {
            "action": "started"
        },
        "public": true,
        "created_at": "2023-10-27T07:50:50Z"
    },
    {
        "id": "32889821702",
        "type": "WatchEvent",
        "actor": {
            "id": 108027865,
            "login": "nickaldwin",
            "display_login": "nickaldwin",
            "gravatar_id": "",
            "url": "https://api.github.com/users/nickaldwin",
            "avatar_url": "https://avatars.githubusercontent.com/u/108027865?"
        },
        "repo": {
            "id": 124678204,
            "name": "aircrack-ng/aircrack-ng",
            "url": "https://api.github.com/repos/aircrack-ng/aircrack-ng"
        },
        "payload": {
            "action": "started"
        },
        "public": true,
        "created_at": "2023-10-27T06:32:07Z"
    },
    {
        "id": "32878675532",
        "type": "WatchEvent",
        "actor": {
            "id": 127569486,
            "login": "CR8VRVLTN",
            "display_login": "CR8VRVLTN",
            "gravatar_id": "",
            "url": "https://api.github.com/users/CR8VRVLTN",
            "avatar_url": "https://avatars.githubusercontent.com/u/127569486?"
        },
        "repo": {
            "id": 124678204,
            "name": "aircrack-ng/aircrack-ng",
            "url": "https://api.github.com/repos/aircrack-ng/aircrack-ng"
        },
        "payload": {
            "action": "started"
        },
        "public": true,
        "created_at": "2023-10-26T18:42:20Z"
    },
    {
        "id": "32875836095",
        "type": "WatchEvent",
        "actor": {
            "id": 25042646,
            "login": "properchopsticks",
            "display_login": "properchopsticks",
            "gravatar_id": "",
            "url": "https://api.github.com/users/properchopsticks",
            "avatar_url": "https://avatars.githubusercontent.com/u/25042646?"
        },
        "repo": {
            "id": 124678204,
            "name": "aircrack-ng/aircrack-ng",
            "url": "https://api.github.com/repos/aircrack-ng/aircrack-ng"
        },
        "payload": {
            "action": "started"
        },
        "public": true,
        "created_at": "2023-10-26T16:47:31Z"
    },
    {
        "id": "32850541152",
        "type": "WatchEvent",
        "actor": {
            "id": 113670501,
            "login": "jagalabi",
            "display_login": "jagalabi",
            "gravatar_id": "",
            "url": "https://api.github.com/users/jagalabi",
            "avatar_url": "https://avatars.githubusercontent.com/u/113670501?"
        },
        "repo": {
            "id": 124678204,
            "name": "aircrack-ng/aircrack-ng",
            "url": "https://api.github.com/repos/aircrack-ng/aircrack-ng"
        },
        "payload": {
            "action": "started"
        },
        "public": true,
        "created_at": "2023-10-25T22:04:15Z"
    },
    {
        "id": "32839360493",
        "type": "WatchEvent",
        "actor": {
            "id": 9622749,
            "login": "nehSgnaiL",
            "display_login": "nehSgnaiL",
            "gravatar_id": "",
            "url": "https://api.github.com/users/nehSgnaiL",
            "avatar_url": "https://avatars.githubusercontent.com/u/9622749?"
        },
        "repo": {
            "id": 124678204,
            "name": "aircrack-ng/aircrack-ng",
            "url": "https://api.github.com/repos/aircrack-ng/aircrack-ng"
        },
        "payload": {
            "action": "started"
        },
        "public": true,
        "created_at": "2023-10-25T14:43:53Z"
    },
    {
        "id": "32839349098",
        "type": "WatchEvent",
        "actor": {
            "id": 9622749,
            "login": "nehSgnaiL",
            "display_login": "nehSgnaiL",
            "gravatar_id": "",
            "url": "https://api.github.com/users/nehSgnaiL",
            "avatar_url": "https://avatars.githubusercontent.com/u/9622749?"
        },
        "repo": {
            "id": 124678204,
            "name": "aircrack-ng/aircrack-ng",
            "url": "https://api.github.com/repos/aircrack-ng/aircrack-ng"
        },
        "payload": {
            "action": "started"
        },
        "public": true,
        "created_at": "2023-10-25T14:43:33Z"
    },
    {
        "id": "32839300201",
        "type": "WatchEvent",
        "actor": {
            "id": 9622749,
            "login": "nehSgnaiL",
            "display_login": "nehSgnaiL",
            "gravatar_id": "",
            "url": "https://api.github.com/users/nehSgnaiL",
            "avatar_url": "https://avatars.githubusercontent.com/u/9622749?"
        },
        "repo": {
            "id": 124678204,
            "name": "aircrack-ng/aircrack-ng",
            "url": "https://api.github.com/repos/aircrack-ng/aircrack-ng"
        },
        "payload": {
            "action": "started"
        },
        "public": true,
        "created_at": "2023-10-25T14:42:07Z"
    },
    {
        "id": "32838069369",
        "type": "ForkEvent",
        "actor": {
            "id": 64043869,
            "login": "culliard",
            "display_login": "culliard",
            "gravatar_id": "",
            "url": "https://api.github.com/users/culliard",
            "avatar_url": "https://avatars.githubusercontent.com/u/64043869?"
        },
        "repo": {
            "id": 124678204,
            "name": "aircrack-ng/aircrack-ng",
            "url": "https://api.github.com/repos/aircrack-ng/aircrack-ng"
        },
        "payload": {
            "forkee": {
                "id": 709845212,
                "node_id": "R_kgDOKk9g3A",
                "name": "aircrack-ng",
                "full_name": "culliard/aircrack-ng",
                "private": false,
                "owner": {
                    "login": "culliard",
                    "id": 64043869,
                    "node_id": "MDQ6VXNlcjY0MDQzODY5",
                    "avatar_url": "https://avatars.githubusercontent.com/u/64043869?v=4",
                    "gravatar_id": "",
                    "url": "https://api.github.com/users/culliard",
                    "html_url": "https://github.com/culliard",
                    "followers_url": "https://api.github.com/users/culliard/followers",
                    "following_url": "https://api.github.com/users/culliard/following{/other_user}",
                    "gists_url": "https://api.github.com/users/culliard/gists{/gist_id}",
                    "starred_url": "https://api.github.com/users/culliard/starred{/owner}{/repo}",
                    "subscriptions_url": "https://api.github.com/users/culliard/subscriptions",
                    "organizations_url": "https://api.github.com/users/culliard/orgs",
                    "repos_url": "https://api.github.com/users/culliard/repos",
                    "events_url": "https://api.github.com/users/culliard/events{/privacy}",
                    "received_events_url": "https://api.github.com/users/culliard/received_events",
                    "type": "User",
                    "site_admin": false
                },
                "html_url": "https://github.com/culliard/aircrack-ng",
                "description": "WiFi security auditing tools suite",
                "fork": true,
                "url": "https://api.github.com/repos/culliard/aircrack-ng",
                "forks_url": "https://api.github.com/repos/culliard/aircrack-ng/forks",
                "keys_url": "https://api.github.com/repos/culliard/aircrack-ng/keys{/key_id}",
                "collaborators_url": "https://api.github.com/repos/culliard/aircrack-ng/collaborators{/collaborator}",
                "teams_url": "https://api.github.com/repos/culliard/aircrack-ng/teams",
                "hooks_url": "https://api.github.com/repos/culliard/aircrack-ng/hooks",
                "issue_events_url": "https://api.github.com/repos/culliard/aircrack-ng/issues/events{/number}",
                "events_url": "https://api.github.com/repos/culliard/aircrack-ng/events",
                "assignees_url": "https://api.github.com/repos/culliard/aircrack-ng/assignees{/user}",
                "branches_url": "https://api.github.com/repos/culliard/aircrack-ng/branches{/branch}",
                "tags_url": "https://api.github.com/repos/culliard/aircrack-ng/tags",
                "blobs_url": "https://api.github.com/repos/culliard/aircrack-ng/git/blobs{/sha}",
                "git_tags_url": "https://api.github.com/repos/culliard/aircrack-ng/git/tags{/sha}",
                "git_refs_url": "https://api.github.com/repos/culliard/aircrack-ng/git/refs{/sha}",
                "trees_url": "https://api.github.com/repos/culliard/aircrack-ng/git/trees{/sha}",
                "statuses_url": "https://api.github.com/repos/culliard/aircrack-ng/statuses/{sha}",
                "languages_url": "https://api.github.com/repos/culliard/aircrack-ng/languages",
                "stargazers_url": "https://api.github.com/repos/culliard/aircrack-ng/stargazers",
                "contributors_url": "https://api.github.com/repos/culliard/aircrack-ng/contributors",
                "subscribers_url": "https://api.github.com/repos/culliard/aircrack-ng/subscribers",
                "subscription_url": "https://api.github.com/repos/culliard/aircrack-ng/subscription",
                "commits_url": "https://api.github.com/repos/culliard/aircrack-ng/commits{/sha}",
                "git_commits_url": "https://api.github.com/repos/culliard/aircrack-ng/git/commits{/sha}",
                "comments_url": "https://api.github.com/repos/culliard/aircrack-ng/comments{/number}",
                "issue_comment_url": "https://api.github.com/repos/culliard/aircrack-ng/issues/comments{/number}",
                "contents_url": "https://api.github.com/repos/culliard/aircrack-ng/contents/{+path}",
                "compare_url": "https://api.github.com/repos/culliard/aircrack-ng/compare/{base}...{head}",
                "merges_url": "https://api.github.com/repos/culliard/aircrack-ng/merges",
                "archive_url": "https://api.github.com/repos/culliard/aircrack-ng/{archive_format}{/ref}",
                "downloads_url": "https://api.github.com/repos/culliard/aircrack-ng/downloads",
                "issues_url": "https://api.github.com/repos/culliard/aircrack-ng/issues{/number}",
                "pulls_url": "https://api.github.com/repos/culliard/aircrack-ng/pulls{/number}",
                "milestones_url": "https://api.github.com/repos/culliard/aircrack-ng/milestones{/number}",
                "notifications_url": "https://api.github.com/repos/culliard/aircrack-ng/notifications{?since,all,participating}",
                "labels_url": "https://api.github.com/repos/culliard/aircrack-ng/labels{/name}",
                "releases_url": "https://api.github.com/repos/culliard/aircrack-ng/releases{/id}",
                "deployments_url": "https://api.github.com/repos/culliard/aircrack-ng/deployments",
                "created_at": "2023-10-25T14:07:36Z",
                "updated_at": "2023-10-25T14:07:36Z",
                "pushed_at": "2023-10-19T16:45:37Z",
                "git_url": "git://github.com/culliard/aircrack-ng.git",
                "ssh_url": "git@github.com:culliard/aircrack-ng.git",
                "clone_url": "https://github.com/culliard/aircrack-ng.git",
                "svn_url": "https://github.com/culliard/aircrack-ng",
                "homepage": "https://aircrack-ng.org",
                "size": 16872,
                "stargazers_count": 0,
                "watchers_count": 0,
                "language": null,
                "has_issues": false,
                "has_projects": true,
                "has_downloads": true,
                "has_wiki": false,
                "has_pages": false,
                "has_discussions": false,
                "forks_count": 0,
                "mirror_url": null,
                "archived": false,
                "disabled": false,
                "open_issues_count": 0,
                "license": {
                    "key": "gpl-2.0",
                    "name": "GNU General Public License v2.0",
                    "spdx_id": "GPL-2.0",
                    "url": "https://api.github.com/licenses/gpl-2.0",
                    "node_id": "MDc6TGljZW5zZTg="
                },
                "allow_forking": true,
                "is_template": false,
                "web_commit_signoff_required": false,
                "topics": [],
                "visibility": "public",
                "forks": 0,
                "open_issues": 0,
                "watchers": 0,
                "default_branch": "master",
                "public": true
            }
        },
        "public": true,
        "created_at": "2023-10-25T14:07:38Z"
    },
    {
        "id": "32832216149",
        "type": "WatchEvent",
        "actor": {
            "id": 70669893,
            "login": "Cyber-Freak999",
            "display_login": "Cyber-Freak999",
            "gravatar_id": "",
            "url": "https://api.github.com/users/Cyber-Freak999",
            "avatar_url": "https://avatars.githubusercontent.com/u/70669893?"
        },
        "repo": {
            "id": 124678204,
            "name": "aircrack-ng/aircrack-ng",
            "url": "https://api.github.com/repos/aircrack-ng/aircrack-ng"
        },
        "payload": {
            "action": "started"
        },
        "public": true,
        "created_at": "2023-10-25T10:58:33Z"
    },
    {
        "id": "32827808825",
        "type": "ForkEvent",
        "actor": {
            "id": 64043869,
            "login": "culliard",
            "display_login": "culliard",
            "gravatar_id": "",
            "url": "https://api.github.com/users/culliard",
            "avatar_url": "https://avatars.githubusercontent.com/u/64043869?"
        },
        "repo": {
            "id": 124678204,
            "name": "aircrack-ng/aircrack-ng",
            "url": "https://api.github.com/repos/aircrack-ng/aircrack-ng"
        },
        "payload": {
            "forkee": {
                "id": 709705297,
                "node_id": "R_kgDOKk0-UQ",
                "name": "aircrack-ng",
                "full_name": "culliard/aircrack-ng",
                "private": false,
                "owner": {
                    "login": "culliard",
                    "id": 64043869,
                    "node_id": "MDQ6VXNlcjY0MDQzODY5",
                    "avatar_url": "https://avatars.githubusercontent.com/u/64043869?v=4",
                    "gravatar_id": "",
                    "url": "https://api.github.com/users/culliard",
                    "html_url": "https://github.com/culliard",
                    "followers_url": "https://api.github.com/users/culliard/followers",
                    "following_url": "https://api.github.com/users/culliard/following{/other_user}",
                    "gists_url": "https://api.github.com/users/culliard/gists{/gist_id}",
                    "starred_url": "https://api.github.com/users/culliard/starred{/owner}{/repo}",
                    "subscriptions_url": "https://api.github.com/users/culliard/subscriptions",
                    "organizations_url": "https://api.github.com/users/culliard/orgs",
                    "repos_url": "https://api.github.com/users/culliard/repos",
                    "events_url": "https://api.github.com/users/culliard/events{/privacy}",
                    "received_events_url": "https://api.github.com/users/culliard/received_events",
                    "type": "User",
                    "site_admin": false
                },
                "html_url": "https://github.com/culliard/aircrack-ng",
                "description": "WiFi security auditing tools suite",
                "fork": true,
                "url": "https://api.github.com/repos/culliard/aircrack-ng",
                "forks_url": "https://api.github.com/repos/culliard/aircrack-ng/forks",
                "keys_url": "https://api.github.com/repos/culliard/aircrack-ng/keys{/key_id}",
                "collaborators_url": "https://api.github.com/repos/culliard/aircrack-ng/collaborators{/collaborator}",
                "teams_url": "https://api.github.com/repos/culliard/aircrack-ng/teams",
                "hooks_url": "https://api.github.com/repos/culliard/aircrack-ng/hooks",
                "issue_events_url": "https://api.github.com/repos/culliard/aircrack-ng/issues/events{/number}",
                "events_url": "https://api.github.com/repos/culliard/aircrack-ng/events",
                "assignees_url": "https://api.github.com/repos/culliard/aircrack-ng/assignees{/user}",
                "branches_url": "https://api.github.com/repos/culliard/aircrack-ng/branches{/branch}",
                "tags_url": "https://api.github.com/repos/culliard/aircrack-ng/tags",
                "blobs_url": "https://api.github.com/repos/culliard/aircrack-ng/git/blobs{/sha}",
                "git_tags_url": "https://api.github.com/repos/culliard/aircrack-ng/git/tags{/sha}",
                "git_refs_url": "https://api.github.com/repos/culliard/aircrack-ng/git/refs{/sha}",
                "trees_url": "https://api.github.com/repos/culliard/aircrack-ng/git/trees{/sha}",
                "statuses_url": "https://api.github.com/repos/culliard/aircrack-ng/statuses/{sha}",
                "languages_url": "https://api.github.com/repos/culliard/aircrack-ng/languages",
                "stargazers_url": "https://api.github.com/repos/culliard/aircrack-ng/stargazers",
                "contributors_url": "https://api.github.com/repos/culliard/aircrack-ng/contributors",
                "subscribers_url": "https://api.github.com/repos/culliard/aircrack-ng/subscribers",
                "subscription_url": "https://api.github.com/repos/culliard/aircrack-ng/subscription",
                "commits_url": "https://api.github.com/repos/culliard/aircrack-ng/commits{/sha}",
                "git_commits_url": "https://api.github.com/repos/culliard/aircrack-ng/git/commits{/sha}",
                "comments_url": "https://api.github.com/repos/culliard/aircrack-ng/comments{/number}",
                "issue_comment_url": "https://api.github.com/repos/culliard/aircrack-ng/issues/comments{/number}",
                "contents_url": "https://api.github.com/repos/culliard/aircrack-ng/contents/{+path}",
                "compare_url": "https://api.github.com/repos/culliard/aircrack-ng/compare/{base}...{head}",
                "merges_url": "https://api.github.com/repos/culliard/aircrack-ng/merges",
                "archive_url": "https://api.github.com/repos/culliard/aircrack-ng/{archive_format}{/ref}",
                "downloads_url": "https://api.github.com/repos/culliard/aircrack-ng/downloads",
                "issues_url": "https://api.github.com/repos/culliard/aircrack-ng/issues{/number}",
                "pulls_url": "https://api.github.com/repos/culliard/aircrack-ng/pulls{/number}",
                "milestones_url": "https://api.github.com/repos/culliard/aircrack-ng/milestones{/number}",
                "notifications_url": "https://api.github.com/repos/culliard/aircrack-ng/notifications{?since,all,participating}",
                "labels_url": "https://api.github.com/repos/culliard/aircrack-ng/labels{/name}",
                "releases_url": "https://api.github.com/repos/culliard/aircrack-ng/releases{/id}",
                "deployments_url": "https://api.github.com/repos/culliard/aircrack-ng/deployments",
                "created_at": "2023-10-25T08:27:50Z",
                "updated_at": "2023-10-25T08:27:50Z",
                "pushed_at": "2023-10-19T16:45:37Z",
                "git_url": "git://github.com/culliard/aircrack-ng.git",
                "ssh_url": "git@github.com:culliard/aircrack-ng.git",
                "clone_url": "https://github.com/culliard/aircrack-ng.git",
                "svn_url": "https://github.com/culliard/aircrack-ng",
                "homepage": "https://aircrack-ng.org",
                "size": 16872,
                "stargazers_count": 0,
                "watchers_count": 0,
                "language": null,
                "has_issues": false,
                "has_projects": true,
                "has_downloads": true,
                "has_wiki": false,
                "has_pages": false,
                "has_discussions": false,
                "forks_count": 0,
                "mirror_url": null,
                "archived": false,
                "disabled": false,
                "open_issues_count": 0,
                "license": null,
                "allow_forking": true,
                "is_template": false,
                "web_commit_signoff_required": false,
                "topics": [],
                "visibility": "public",
                "forks": 0,
                "open_issues": 0,
                "watchers": 0,
                "default_branch": "main",
                "public": true
            }
        },
        "public": true,
        "created_at": "2023-10-25T08:27:52Z"
    },
    {
        "id": "32817749921",
        "type": "WatchEvent",
        "actor": {
            "id": 122464743,
            "login": "slytherinheir24",
            "display_login": "slytherinheir24",
            "gravatar_id": "",
            "url": "https://api.github.com/users/slytherinheir24",
            "avatar_url": "https://avatars.githubusercontent.com/u/122464743?"
        },
        "repo": {
            "id": 124678204,
            "name": "aircrack-ng/aircrack-ng",
            "url": "https://api.github.com/repos/aircrack-ng/aircrack-ng"
        },
        "payload": {
            "action": "started"
        },
        "public": true,
        "created_at": "2023-10-24T22:12:27Z"
    },
    {
        "id": "32804167076",
        "type": "IssueCommentEvent",
        "actor": {
            "id": 64043869,
            "login": "culliard",
            "display_login": "culliard",
            "gravatar_id": "",
            "url": "https://api.github.com/users/culliard",
            "avatar_url": "https://avatars.githubusercontent.com/u/64043869?"
        },
        "repo": {
            "id": 124678204,
            "name": "aircrack-ng/aircrack-ng",
            "url": "https://api.github.com/repos/aircrack-ng/aircrack-ng"
        },
        "payload": {
            "action": "created",
            "issue": {
                "url": "https://api.github.com/repos/aircrack-ng/aircrack-ng/issues/2584",
                "repository_url": "https://api.github.com/repos/aircrack-ng/aircrack-ng",
                "labels_url": "https://api.github.com/repos/aircrack-ng/aircrack-ng/issues/2584/labels{/name}",
                "comments_url": "https://api.github.com/repos/aircrack-ng/aircrack-ng/issues/2584/comments",
                "events_url": "https://api.github.com/repos/aircrack-ng/aircrack-ng/issues/2584/events",
                "html_url": "https://github.com/aircrack-ng/aircrack-ng/issues/2584",
                "id": 1952174829,
                "node_id": "I_kwDOB25wPM50W9Lt",
                "number": 2584,
                "title": "airodump-ng wifi6e (6ghz) \"band\" argument support",
                "user": {
                    "login": "OscarAkaElvis",
                    "id": 5803348,
                    "node_id": "MDQ6VXNlcjU4MDMzNDg=",
                    "avatar_url": "https://avatars.githubusercontent.com/u/5803348?v=4",
                    "gravatar_id": "",
                    "url": "https://api.github.com/users/OscarAkaElvis",
                    "html_url": "https://github.com/OscarAkaElvis",
                    "followers_url": "https://api.github.com/users/OscarAkaElvis/followers",
                    "following_url": "https://api.github.com/users/OscarAkaElvis/following{/other_user}",
                    "gists_url": "https://api.github.com/users/OscarAkaElvis/gists{/gist_id}",
                    "starred_url": "https://api.github.com/users/OscarAkaElvis/starred{/owner}{/repo}",
                    "subscriptions_url": "https://api.github.com/users/OscarAkaElvis/subscriptions",
                    "organizations_url": "https://api.github.com/users/OscarAkaElvis/orgs",
                    "repos_url": "https://api.github.com/users/OscarAkaElvis/repos",
                    "events_url": "https://api.github.com/users/OscarAkaElvis/events{/privacy}",
                    "received_events_url": "https://api.github.com/users/OscarAkaElvis/received_events",
                    "type": "User",
                    "site_admin": false
                },
                "labels": [],
                "state": "open",
                "locked": false,
                "assignee": null,
                "assignees": [],
                "milestone": null,
                "comments": 2,
                "created_at": "2023-10-19T12:45:43Z",
                "updated_at": "2023-10-24T13:26:43Z",
                "closed_at": null,
                "author_association": "NONE",
                "active_lock_reason": null,
                "body": "Hello, I saw in aircrack-ng v1.7 changelog that 6ghz feature was added. I tested it and yeah, my wifi6e card airodump scan is now hopping through new channels, but what I miss is a configuration argument to handle this in the same way can be done for 5ghz. I mean the \"--band\" argument for the airodump command line.\r\n\r\n--band bg -> for 2.4ghz\r\n--band abg -> for 5ghz\r\n--band xxxx <- something for 6ghz\r\n\r\nIt could be nice to have this feature for the near future. That will allow to the scripters like me to handle this new band in the same way. Thanks.\r\n",
                "reactions": {
                    "url": "https://api.github.com/repos/aircrack-ng/aircrack-ng/issues/2584/reactions",
                    "total_count": 0,
                    "+1": 0,
                    "-1": 0,
                    "laugh": 0,
                    "hooray": 0,
                    "confused": 0,
                    "heart": 0,
                    "rocket": 0,
                    "eyes": 0
                },
                "timeline_url": "https://api.github.com/repos/aircrack-ng/aircrack-ng/issues/2584/timeline",
                "performed_via_github_app": null,
                "state_reason": null
            },
            "comment": {
                "url": "https://api.github.com/repos/aircrack-ng/aircrack-ng/issues/comments/1777203248",
                "html_url": "https://github.com/aircrack-ng/aircrack-ng/issues/2584#issuecomment-1777203248",
                "issue_url": "https://api.github.com/repos/aircrack-ng/aircrack-ng/issues/2584",
                "id": 1777203248,
                "node_id": "IC_kwDOB25wPM5p7fgw",
                "user": {
                    "login": "culliard",
                    "id": 64043869,
                    "node_id": "MDQ6VXNlcjY0MDQzODY5",
                    "avatar_url": "https://avatars.githubusercontent.com/u/64043869?v=4",
                    "gravatar_id": "",
                    "url": "https://api.github.com/users/culliard",
                    "html_url": "https://github.com/culliard",
                    "followers_url": "https://api.github.com/users/culliard/followers",
                    "following_url": "https://api.github.com/users/culliard/following{/other_user}",
                    "gists_url": "https://api.github.com/users/culliard/gists{/gist_id}",
                    "starred_url": "https://api.github.com/users/culliard/starred{/owner}{/repo}",
                    "subscriptions_url": "https://api.github.com/users/culliard/subscriptions",
                    "organizations_url": "https://api.github.com/users/culliard/orgs",
                    "repos_url": "https://api.github.com/users/culliard/repos",
                    "events_url": "https://api.github.com/users/culliard/events{/privacy}",
                    "received_events_url": "https://api.github.com/users/culliard/received_events",
                    "type": "User",
                    "site_admin": false
                },
                "created_at": "2023-10-24T13:26:42Z",
                "updated_at": "2023-10-24T13:26:42Z",
                "author_association": "NONE",
                "body": "+1\r\n\r\nNote some related isues:\r\n[2205](https://github.com/aircrack-ng/aircrack-ng/issues/2205)\r\n[2274](https://github.com/aircrack-ng/aircrack-ng/issues/2274)",
                "reactions": {
                    "url": "https://api.github.com/repos/aircrack-ng/aircrack-ng/issues/comments/1777203248/reactions",
                    "total_count": 0,
                    "+1": 0,
                    "-1": 0,
                    "laugh": 0,
                    "hooray": 0,
                    "confused": 0,
                    "heart": 0,
                    "rocket": 0,
                    "eyes": 0
                },
                "performed_via_github_app": null
            }
        },
        "public": true,
        "created_at": "2023-10-24T13:26:43Z"
    },
    {
        "id": "32804086574",
        "type": "IssueCommentEvent",
        "actor": {
            "id": 64043869,
            "login": "culliard",
            "display_login": "culliard",
            "gravatar_id": "",
            "url": "https://api.github.com/users/culliard",
            "avatar_url": "https://avatars.githubusercontent.com/u/64043869?"
        },
        "repo": {
            "id": 124678204,
            "name": "aircrack-ng/aircrack-ng",
            "url": "https://api.github.com/repos/aircrack-ng/aircrack-ng"
        },
        "payload": {
            "action": "created",
            "issue": {
                "url": "https://api.github.com/repos/aircrack-ng/aircrack-ng/issues/2274",
                "repository_url": "https://api.github.com/repos/aircrack-ng/aircrack-ng",
                "labels_url": "https://api.github.com/repos/aircrack-ng/aircrack-ng/issues/2274/labels{/name}",
                "comments_url": "https://api.github.com/repos/aircrack-ng/aircrack-ng/issues/2274/comments",
                "events_url": "https://api.github.com/repos/aircrack-ng/aircrack-ng/issues/2274/events",
                "html_url": "https://github.com/aircrack-ng/aircrack-ng/issues/2274",
                "id": 1046259466,
                "node_id": "I_kwDOB25wPM4-XKcK",
                "number": 2274,
                "title": "Add 'band 6' to airodump-ng for WiFi 6E 6GHz channels",
                "user": {
                    "login": "aircrack-ng",
                    "id": 4042925,
                    "node_id": "MDQ6VXNlcjQwNDI5MjU=",
                    "avatar_url": "https://avatars.githubusercontent.com/u/4042925?v=4",
                    "gravatar_id": "",
                    "url": "https://api.github.com/users/aircrack-ng",
                    "html_url": "https://github.com/aircrack-ng",
                    "followers_url": "https://api.github.com/users/aircrack-ng/followers",
                    "following_url": "https://api.github.com/users/aircrack-ng/following{/other_user}",
                    "gists_url": "https://api.github.com/users/aircrack-ng/gists{/gist_id}",
                    "starred_url": "https://api.github.com/users/aircrack-ng/starred{/owner}{/repo}",
                    "subscriptions_url": "https://api.github.com/users/aircrack-ng/subscriptions",
                    "organizations_url": "https://api.github.com/users/aircrack-ng/orgs",
                    "repos_url": "https://api.github.com/users/aircrack-ng/repos",
                    "events_url": "https://api.github.com/users/aircrack-ng/events{/privacy}",
                    "received_events_url": "https://api.github.com/users/aircrack-ng/received_events",
                    "type": "User",
                    "site_admin": false
                },
                "labels": [
                    {
                        "id": 862704724,
                        "node_id": "MDU6TGFiZWw4NjI3MDQ3MjQ=",
                        "url": "https://api.github.com/repos/aircrack-ng/aircrack-ng/labels/%23aireplay-ng",
                        "name": "#aireplay-ng",
                        "color": "0000aa",
                        "default": false,
                        "description": null
                    },
                    {
                        "id": 862704728,
                        "node_id": "MDU6TGFiZWw4NjI3MDQ3Mjg=",
                        "url": "https://api.github.com/repos/aircrack-ng/aircrack-ng/labels/%23airodump-ng",
                        "name": "#airodump-ng",
                        "color": "0000aa",
                        "default": false,
                        "description": null
                    },
                    {
                        "id": 862704851,
                        "node_id": "MDU6TGFiZWw4NjI3MDQ4NTE=",
                        "url": "https://api.github.com/repos/aircrack-ng/aircrack-ng/labels/%23osdep",
                        "name": "#osdep",
                        "color": "0000aa",
                        "default": false,
                        "description": null
                    }
                ],
                "state": "open",
                "locked": false,
                "assignee": null,
                "assignees": [],
                "milestone": null,
                "comments": 38,
                "created_at": "2021-11-05T21:33:23Z",
                "updated_at": "2023-10-24T13:24:09Z",
                "closed_at": null,
                "author_association": "OWNER",
                "active_lock_reason": null,
                "body": "# Details\r\n\r\nWiFi 6E added a bunch of channels in the 6GHz band. Some work has already been done to allow these channels by frequency (#2273), but we need to add the channel numbers as well. \r\n\r\nPlus there might be some work needed in osdep and aireplay-ng.\r\n\r\n## Related\r\n\r\n#2205",
                "reactions": {
                    "url": "https://api.github.com/repos/aircrack-ng/aircrack-ng/issues/2274/reactions",
                    "total_count": 0,
                    "+1": 0,
                    "-1": 0,
                    "laugh": 0,
                    "hooray": 0,
                    "confused": 0,
                    "heart": 0,
                    "rocket": 0,
                    "eyes": 0
                },
                "timeline_url": "https://api.github.com/repos/aircrack-ng/aircrack-ng/issues/2274/timeline",
                "performed_via_github_app": null,
                "state_reason": null
            },
            "comment": {
                "url": "https://api.github.com/repos/aircrack-ng/aircrack-ng/issues/comments/1777198971",
                "html_url": "https://github.com/aircrack-ng/aircrack-ng/issues/2274#issuecomment-1777198971",
                "issue_url": "https://api.github.com/repos/aircrack-ng/aircrack-ng/issues/2274",
                "id": 1777198971,
                "node_id": "IC_kwDOB25wPM5p7ed7",
                "user": {
                    "login": "culliard",
                    "id": 64043869,
                    "node_id": "MDQ6VXNlcjY0MDQzODY5",
                    "avatar_url": "https://avatars.githubusercontent.com/u/64043869?v=4",
                    "gravatar_id": "",
                    "url": "https://api.github.com/users/culliard",
                    "html_url": "https://github.com/culliard",
                    "followers_url": "https://api.github.com/users/culliard/followers",
                    "following_url": "https://api.github.com/users/culliard/following{/other_user}",
                    "gists_url": "https://api.github.com/users/culliard/gists{/gist_id}",
                    "starred_url": "https://api.github.com/users/culliard/starred{/owner}{/repo}",
                    "subscriptions_url": "https://api.github.com/users/culliard/subscriptions",
                    "organizations_url": "https://api.github.com/users/culliard/orgs",
                    "repos_url": "https://api.github.com/users/culliard/repos",
                    "events_url": "https://api.github.com/users/culliard/events{/privacy}",
                    "received_events_url": "https://api.github.com/users/culliard/received_events",
                    "type": "User",
                    "site_admin": false
                },
                "created_at": "2023-10-24T13:24:09Z",
                "updated_at": "2023-10-24T13:24:09Z",
                "author_association": "NONE",
                "body": "In my case it takes 30 seconds (ALFA AWUS036AXM) to check frequencies\r\n\r\n`sudo airodump-ng -a -C 5935-7115 wlan0mon`\r\n\r\nMore annoying though, is that the output lists my access point which is on 2.4 GHz (channel 1)\r\n\r\nI'm running aircrack 1.7",
                "reactions": {
                    "url": "https://api.github.com/repos/aircrack-ng/aircrack-ng/issues/comments/1777198971/reactions",
                    "total_count": 0,
                    "+1": 0,
                    "-1": 0,
                    "laugh": 0,
                    "hooray": 0,
                    "confused": 0,
                    "heart": 0,
                    "rocket": 0,
                    "eyes": 0
                },
                "performed_via_github_app": null
            }
        },
        "public": true,
        "created_at": "2023-10-24T13:24:10Z"
    },
    {
        "id": "32803634865",
        "type": "WatchEvent",
        "actor": {
            "id": 71203851,
            "login": "diamant3",
            "display_login": "diamant3",
            "gravatar_id": "",
            "url": "https://api.github.com/users/diamant3",
            "avatar_url": "https://avatars.githubusercontent.com/u/71203851?"
        },
        "repo": {
            "id": 124678204,
            "name": "aircrack-ng/aircrack-ng",
            "url": "https://api.github.com/repos/aircrack-ng/aircrack-ng"
        },
        "payload": {
            "action": "started"
        },
        "public": true,
        "created_at": "2023-10-24T13:09:43Z"
    },
    {
        "id": "32778855750",
        "type": "ForkEvent",
        "actor": {
            "id": 72488360,
            "login": "PythonHacker24",
            "display_login": "PythonHacker24",
            "gravatar_id": "",
            "url": "https://api.github.com/users/PythonHacker24",
            "avatar_url": "https://avatars.githubusercontent.com/u/72488360?"
        },
        "repo": {
            "id": 124678204,
            "name": "aircrack-ng/aircrack-ng",
            "url": "https://api.github.com/repos/aircrack-ng/aircrack-ng"
        },
        "payload": {
            "forkee": {
                "id": 708923295,
                "node_id": "R_kgDOKkFPnw",
                "name": "aircrack-ng",
                "full_name": "PythonHacker24/aircrack-ng",
                "private": false,
                "owner": {
                    "login": "PythonHacker24",
                    "id": 72488360,
                    "node_id": "MDQ6VXNlcjcyNDg4MzYw",
                    "avatar_url": "https://avatars.githubusercontent.com/u/72488360?v=4",
                    "gravatar_id": "",
                    "url": "https://api.github.com/users/PythonHacker24",
                    "html_url": "https://github.com/PythonHacker24",
                    "followers_url": "https://api.github.com/users/PythonHacker24/followers",
                    "following_url": "https://api.github.com/users/PythonHacker24/following{/other_user}",
                    "gists_url": "https://api.github.com/users/PythonHacker24/gists{/gist_id}",
                    "starred_url": "https://api.github.com/users/PythonHacker24/starred{/owner}{/repo}",
                    "subscriptions_url": "https://api.github.com/users/PythonHacker24/subscriptions",
                    "organizations_url": "https://api.github.com/users/PythonHacker24/orgs",
                    "repos_url": "https://api.github.com/users/PythonHacker24/repos",
                    "events_url": "https://api.github.com/users/PythonHacker24/events{/privacy}",
                    "received_events_url": "https://api.github.com/users/PythonHacker24/received_events",
                    "type": "User",
                    "site_admin": false
                },
                "html_url": "https://github.com/PythonHacker24/aircrack-ng",
                "description": "WiFi security auditing tools suite",
                "fork": true,
                "url": "https://api.github.com/repos/PythonHacker24/aircrack-ng",
                "forks_url": "https://api.github.com/repos/PythonHacker24/aircrack-ng/forks",
                "keys_url": "https://api.github.com/repos/PythonHacker24/aircrack-ng/keys{/key_id}",
                "collaborators_url": "https://api.github.com/repos/PythonHacker24/aircrack-ng/collaborators{/collaborator}",
                "teams_url": "https://api.github.com/repos/PythonHacker24/aircrack-ng/teams",
                "hooks_url": "https://api.github.com/repos/PythonHacker24/aircrack-ng/hooks",
                "issue_events_url": "https://api.github.com/repos/PythonHacker24/aircrack-ng/issues/events{/number}",
                "events_url": "https://api.github.com/repos/PythonHacker24/aircrack-ng/events",
                "assignees_url": "https://api.github.com/repos/PythonHacker24/aircrack-ng/assignees{/user}",
                "branches_url": "https://api.github.com/repos/PythonHacker24/aircrack-ng/branches{/branch}",
                "tags_url": "https://api.github.com/repos/PythonHacker24/aircrack-ng/tags",
                "blobs_url": "https://api.github.com/repos/PythonHacker24/aircrack-ng/git/blobs{/sha}",
                "git_tags_url": "https://api.github.com/repos/PythonHacker24/aircrack-ng/git/tags{/sha}",
                "git_refs_url": "https://api.github.com/repos/PythonHacker24/aircrack-ng/git/refs{/sha}",
                "trees_url": "https://api.github.com/repos/PythonHacker24/aircrack-ng/git/trees{/sha}",
                "statuses_url": "https://api.github.com/repos/PythonHacker24/aircrack-ng/statuses/{sha}",
                "languages_url": "https://api.github.com/repos/PythonHacker24/aircrack-ng/languages",
                "stargazers_url": "https://api.github.com/repos/PythonHacker24/aircrack-ng/stargazers",
                "contributors_url": "https://api.github.com/repos/PythonHacker24/aircrack-ng/contributors",
                "subscribers_url": "https://api.github.com/repos/PythonHacker24/aircrack-ng/subscribers",
                "subscription_url": "https://api.github.com/repos/PythonHacker24/aircrack-ng/subscription",
                "commits_url": "https://api.github.com/repos/PythonHacker24/aircrack-ng/commits{/sha}",
                "git_commits_url": "https://api.github.com/repos/PythonHacker24/aircrack-ng/git/commits{/sha}",
                "comments_url": "https://api.github.com/repos/PythonHacker24/aircrack-ng/comments{/number}",
                "issue_comment_url": "https://api.github.com/repos/PythonHacker24/aircrack-ng/issues/comments{/number}",
                "contents_url": "https://api.github.com/repos/PythonHacker24/aircrack-ng/contents/{+path}",
                "compare_url": "https://api.github.com/repos/PythonHacker24/aircrack-ng/compare/{base}...{head}",
                "merges_url": "https://api.github.com/repos/PythonHacker24/aircrack-ng/merges",
                "archive_url": "https://api.github.com/repos/PythonHacker24/aircrack-ng/{archive_format}{/ref}",
                "downloads_url": "https://api.github.com/repos/PythonHacker24/aircrack-ng/downloads",
                "issues_url": "https://api.github.com/repos/PythonHacker24/aircrack-ng/issues{/number}",
                "pulls_url": "https://api.github.com/repos/PythonHacker24/aircrack-ng/pulls{/number}",
                "milestones_url": "https://api.github.com/repos/PythonHacker24/aircrack-ng/milestones{/number}",
                "notifications_url": "https://api.github.com/repos/PythonHacker24/aircrack-ng/notifications{?since,all,participating}",
                "labels_url": "https://api.github.com/repos/PythonHacker24/aircrack-ng/labels{/name}",
                "releases_url": "https://api.github.com/repos/PythonHacker24/aircrack-ng/releases{/id}",
                "deployments_url": "https://api.github.com/repos/PythonHacker24/aircrack-ng/deployments",
                "created_at": "2023-10-23T16:50:47Z",
                "updated_at": "2023-10-23T16:50:48Z",
                "pushed_at": "2023-10-19T16:45:37Z",
                "git_url": "git://github.com/PythonHacker24/aircrack-ng.git",
                "ssh_url": "git@github.com:PythonHacker24/aircrack-ng.git",
                "clone_url": "https://github.com/PythonHacker24/aircrack-ng.git",
                "svn_url": "https://github.com/PythonHacker24/aircrack-ng",
                "homepage": "https://aircrack-ng.org",
                "size": 16872,
                "stargazers_count": 0,
                "watchers_count": 0,
                "language": null,
                "has_issues": false,
                "has_projects": true,
                "has_downloads": true,
                "has_wiki": false,
                "has_pages": false,
                "has_discussions": false,
                "forks_count": 0,
                "mirror_url": null,
                "archived": false,
                "disabled": false,
                "open_issues_count": 0,
                "license": null,
                "allow_forking": true,
                "is_template": false,
                "web_commit_signoff_required": false,
                "topics": [],
                "visibility": "public",
                "forks": 0,
                "open_issues": 0,
                "watchers": 0,
                "default_branch": "main",
                "public": true
            }
        },
        "public": true,
        "created_at": "2023-10-23T16:50:49Z"
    },
    {
        "id": "32773756141",
        "type": "WatchEvent",
        "actor": {
            "id": 100683661,
            "login": "ANDRVV",
            "display_login": "ANDRVV",
            "gravatar_id": "",
            "url": "https://api.github.com/users/ANDRVV",
            "avatar_url": "https://avatars.githubusercontent.com/u/100683661?"
        },
        "repo": {
            "id": 124678204,
            "name": "aircrack-ng/aircrack-ng",
            "url": "https://api.github.com/repos/aircrack-ng/aircrack-ng"
        },
        "payload": {
            "action": "started"
        },
        "public": true,
        "created_at": "2023-10-23T14:05:39Z"
    },
    {
        "id": "32770716648",
        "type": "WatchEvent",
        "actor": {
            "id": 140842132,
            "login": "Gangboy021",
            "display_login": "Gangboy021",
            "gravatar_id": "",
            "url": "https://api.github.com/users/Gangboy021",
            "avatar_url": "https://avatars.githubusercontent.com/u/140842132?"
        },
        "repo": {
            "id": 124678204,
            "name": "aircrack-ng/aircrack-ng",
            "url": "https://api.github.com/repos/aircrack-ng/aircrack-ng"
        },
        "payload": {
            "action": "started"
        },
        "public": true,
        "created_at": "2023-10-23T12:31:03Z"
    },
    {
        "id": "32768871148",
        "type": "WatchEvent",
        "actor": {
            "id": 5283709,
            "login": "annibuliful",
            "display_login": "annibuliful",
            "gravatar_id": "",
            "url": "https://api.github.com/users/annibuliful",
            "avatar_url": "https://avatars.githubusercontent.com/u/5283709?"
        },
        "repo": {
            "id": 124678204,
            "name": "aircrack-ng/aircrack-ng",
            "url": "https://api.github.com/repos/aircrack-ng/aircrack-ng"
        },
        "payload": {
            "action": "started"
        },
        "public": true,
        "created_at": "2023-10-23T11:22:10Z"
    },
    {
        "id": "32767088749",
        "type": "WatchEvent",
        "actor": {
            "id": 18234839,
            "login": "karmiksan",
            "display_login": "karmiksan",
            "gravatar_id": "",
            "url": "https://api.github.com/users/karmiksan",
            "avatar_url": "https://avatars.githubusercontent.com/u/18234839?"
        },
        "repo": {
            "id": 124678204,
            "name": "aircrack-ng/aircrack-ng",
            "url": "https://api.github.com/repos/aircrack-ng/aircrack-ng"
        },
        "payload": {
            "action": "started"
        },
        "public": true,
        "created_at": "2023-10-23T10:15:45Z"
    },
    {
        "id": "32745500436",
        "type": "ForkEvent",
        "actor": {
            "id": 10899846,
            "login": "walcob",
            "display_login": "walcob",
            "gravatar_id": "",
            "url": "https://api.github.com/users/walcob",
            "avatar_url": "https://avatars.githubusercontent.com/u/10899846?"
        },
        "repo": {
            "id": 124678204,
            "name": "aircrack-ng/aircrack-ng",
            "url": "https://api.github.com/repos/aircrack-ng/aircrack-ng"
        },
        "payload": {
            "forkee": {
                "id": 708212597,
                "node_id": "R_kgDOKjZ3dQ",
                "name": "aircrack-ng",
                "full_name": "walcob/aircrack-ng",
                "private": false,
                "owner": {
                    "login": "walcob",
                    "id": 10899846,
                    "node_id": "MDQ6VXNlcjEwODk5ODQ2",
                    "avatar_url": "https://avatars.githubusercontent.com/u/10899846?v=4",
                    "gravatar_id": "",
                    "url": "https://api.github.com/users/walcob",
                    "html_url": "https://github.com/walcob",
                    "followers_url": "https://api.github.com/users/walcob/followers",
                    "following_url": "https://api.github.com/users/walcob/following{/other_user}",
                    "gists_url": "https://api.github.com/users/walcob/gists{/gist_id}",
                    "starred_url": "https://api.github.com/users/walcob/starred{/owner}{/repo}",
                    "subscriptions_url": "https://api.github.com/users/walcob/subscriptions",
                    "organizations_url": "https://api.github.com/users/walcob/orgs",
                    "repos_url": "https://api.github.com/users/walcob/repos",
                    "events_url": "https://api.github.com/users/walcob/events{/privacy}",
                    "received_events_url": "https://api.github.com/users/walcob/received_events",
                    "type": "User",
                    "site_admin": false
                },
                "html_url": "https://github.com/walcob/aircrack-ng",
                "description": "WiFi security auditing tools suite",
                "fork": true,
                "url": "https://api.github.com/repos/walcob/aircrack-ng",
                "forks_url": "https://api.github.com/repos/walcob/aircrack-ng/forks",
                "keys_url": "https://api.github.com/repos/walcob/aircrack-ng/keys{/key_id}",
                "collaborators_url": "https://api.github.com/repos/walcob/aircrack-ng/collaborators{/collaborator}",
                "teams_url": "https://api.github.com/repos/walcob/aircrack-ng/teams",
                "hooks_url": "https://api.github.com/repos/walcob/aircrack-ng/hooks",
                "issue_events_url": "https://api.github.com/repos/walcob/aircrack-ng/issues/events{/number}",
                "events_url": "https://api.github.com/repos/walcob/aircrack-ng/events",
                "assignees_url": "https://api.github.com/repos/walcob/aircrack-ng/assignees{/user}",
                "branches_url": "https://api.github.com/repos/walcob/aircrack-ng/branches{/branch}",
                "tags_url": "https://api.github.com/repos/walcob/aircrack-ng/tags",
                "blobs_url": "https://api.github.com/repos/walcob/aircrack-ng/git/blobs{/sha}",
                "git_tags_url": "https://api.github.com/repos/walcob/aircrack-ng/git/tags{/sha}",
                "git_refs_url": "https://api.github.com/repos/walcob/aircrack-ng/git/refs{/sha}",
                "trees_url": "https://api.github.com/repos/walcob/aircrack-ng/git/trees{/sha}",
                "statuses_url": "https://api.github.com/repos/walcob/aircrack-ng/statuses/{sha}",
                "languages_url": "https://api.github.com/repos/walcob/aircrack-ng/languages",
                "stargazers_url": "https://api.github.com/repos/walcob/aircrack-ng/stargazers",
                "contributors_url": "https://api.github.com/repos/walcob/aircrack-ng/contributors",
                "subscribers_url": "https://api.github.com/repos/walcob/aircrack-ng/subscribers",
                "subscription_url": "https://api.github.com/repos/walcob/aircrack-ng/subscription",
                "commits_url": "https://api.github.com/repos/walcob/aircrack-ng/commits{/sha}",
                "git_commits_url": "https://api.github.com/repos/walcob/aircrack-ng/git/commits{/sha}",
                "comments_url": "https://api.github.com/repos/walcob/aircrack-ng/comments{/number}",
                "issue_comment_url": "https://api.github.com/repos/walcob/aircrack-ng/issues/comments{/number}",
                "contents_url": "https://api.github.com/repos/walcob/aircrack-ng/contents/{+path}",
                "compare_url": "https://api.github.com/repos/walcob/aircrack-ng/compare/{base}...{head}",
                "merges_url": "https://api.github.com/repos/walcob/aircrack-ng/merges",
                "archive_url": "https://api.github.com/repos/walcob/aircrack-ng/{archive_format}{/ref}",
                "downloads_url": "https://api.github.com/repos/walcob/aircrack-ng/downloads",
                "issues_url": "https://api.github.com/repos/walcob/aircrack-ng/issues{/number}",
                "pulls_url": "https://api.github.com/repos/walcob/aircrack-ng/pulls{/number}",
                "milestones_url": "https://api.github.com/repos/walcob/aircrack-ng/milestones{/number}",
                "notifications_url": "https://api.github.com/repos/walcob/aircrack-ng/notifications{?since,all,participating}",
                "labels_url": "https://api.github.com/repos/walcob/aircrack-ng/labels{/name}",
                "releases_url": "https://api.github.com/repos/walcob/aircrack-ng/releases{/id}",
                "deployments_url": "https://api.github.com/repos/walcob/aircrack-ng/deployments",
                "created_at": "2023-10-21T21:30:59Z",
                "updated_at": "2023-10-21T21:31:00Z",
                "pushed_at": "2023-10-19T16:45:37Z",
                "git_url": "git://github.com/walcob/aircrack-ng.git",
                "ssh_url": "git@github.com:walcob/aircrack-ng.git",
                "clone_url": "https://github.com/walcob/aircrack-ng.git",
                "svn_url": "https://github.com/walcob/aircrack-ng",
                "homepage": "https://aircrack-ng.org",
                "size": 16872,
                "stargazers_count": 0,
                "watchers_count": 0,
                "language": null,
                "has_issues": false,
                "has_projects": true,
                "has_downloads": true,
                "has_wiki": false,
                "has_pages": false,
                "has_discussions": false,
                "forks_count": 0,
                "mirror_url": null,
                "archived": false,
                "disabled": false,
                "open_issues_count": 0,
                "license": {
                    "key": "gpl-2.0",
                    "name": "GNU General Public License v2.0",
                    "spdx_id": "GPL-2.0",
                    "url": "https://api.github.com/licenses/gpl-2.0",
                    "node_id": "MDc6TGljZW5zZTg="
                },
                "allow_forking": true,
                "is_template": false,
                "web_commit_signoff_required": false,
                "topics": [],
                "visibility": "public",
                "forks": 0,
                "open_issues": 0,
                "watchers": 0,
                "default_branch": "main",
                "public": true
            }
        },
        "public": true,
        "created_at": "2023-10-21T21:31:01Z"
    },
    {
        "id": "32744373216",
        "type": "WatchEvent",
        "actor": {
            "id": 127901233,
            "login": "filexploit",
            "display_login": "filexploit",
            "gravatar_id": "",
            "url": "https://api.github.com/users/filexploit",
            "avatar_url": "https://avatars.githubusercontent.com/u/127901233?"
        },
        "repo": {
            "id": 124678204,
            "name": "aircrack-ng/aircrack-ng",
            "url": "https://api.github.com/repos/aircrack-ng/aircrack-ng"
        },
        "payload": {
            "action": "started"
        },
        "public": true,
        "created_at": "2023-10-21T18:41:33Z"
    },
    {
        "id": "32738705772",
        "type": "WatchEvent",
        "actor": {
            "id": 69758022,
            "login": "tuanductran",
            "display_login": "tuanductran",
            "gravatar_id": "",
            "url": "https://api.github.com/users/tuanductran",
            "avatar_url": "https://avatars.githubusercontent.com/u/69758022?"
        },
        "repo": {
            "id": 124678204,
            "name": "aircrack-ng/aircrack-ng",
            "url": "https://api.github.com/repos/aircrack-ng/aircrack-ng"
        },
        "payload": {
            "action": "started"
        },
        "public": true,
        "created_at": "2023-10-21T05:52:01Z"
    },
    {
        "id": "32736455789",
        "type": "WatchEvent",
        "actor": {
            "id": 132273160,
            "login": "lxluin",
            "display_login": "lxluin",
            "gravatar_id": "",
            "url": "https://api.github.com/users/lxluin",
            "avatar_url": "https://avatars.githubusercontent.com/u/132273160?"
        },
        "repo": {
            "id": 124678204,
            "name": "aircrack-ng/aircrack-ng",
            "url": "https://api.github.com/repos/aircrack-ng/aircrack-ng"
        },
        "payload": {
            "action": "started"
        },
        "public": true,
        "created_at": "2023-10-21T00:33:57Z"
    },
    {
        "id": "32736144354",
        "type": "WatchEvent",
        "actor": {
            "id": 62893792,
            "login": "KnightsWhoSayNi0",
            "display_login": "KnightsWhoSayNi0",
            "gravatar_id": "",
            "url": "https://api.github.com/users/KnightsWhoSayNi0",
            "avatar_url": "https://avatars.githubusercontent.com/u/62893792?"
        },
        "repo": {
            "id": 124678204,
            "name": "aircrack-ng/aircrack-ng",
            "url": "https://api.github.com/repos/aircrack-ng/aircrack-ng"
        },
        "payload": {
            "action": "started"
        },
        "public": true,
        "created_at": "2023-10-20T23:59:29Z"
    },
    {
        "id": "32721987993",
        "type": "WatchEvent",
        "actor": {
            "id": 28847642,
            "login": "gmanprime",
            "display_login": "gmanprime",
            "gravatar_id": "",
            "url": "https://api.github.com/users/gmanprime",
            "avatar_url": "https://avatars.githubusercontent.com/u/28847642?"
        },
        "repo": {
            "id": 124678204,
            "name": "aircrack-ng/aircrack-ng",
            "url": "https://api.github.com/repos/aircrack-ng/aircrack-ng"
        },
        "payload": {
            "action": "started"
        },
        "public": true,
        "created_at": "2023-10-20T12:37:53Z"
    },
    {
        "id": "32720059580",
        "type": "WatchEvent",
        "actor": {
            "id": 127231122,
            "login": "chgsyh",
            "display_login": "chgsyh",
            "gravatar_id": "",
            "url": "https://api.github.com/users/chgsyh",
            "avatar_url": "https://avatars.githubusercontent.com/u/127231122?"
        },
        "repo": {
            "id": 124678204,
            "name": "aircrack-ng/aircrack-ng",
            "url": "https://api.github.com/repos/aircrack-ng/aircrack-ng"
        },
        "payload": {
            "action": "started"
        },
        "public": true,
        "created_at": "2023-10-20T11:21:21Z"
    },
    {
        "id": "32719659143",
        "type": "IssueCommentEvent",
        "actor": {
            "id": 239485,
            "login": "bdrung",
            "display_login": "bdrung",
            "gravatar_id": "",
            "url": "https://api.github.com/users/bdrung",
            "avatar_url": "https://avatars.githubusercontent.com/u/239485?"
        },
        "repo": {
            "id": 124678204,
            "name": "aircrack-ng/aircrack-ng",
            "url": "https://api.github.com/repos/aircrack-ng/aircrack-ng"
        },
        "payload": {
            "action": "created",
            "issue": {
                "url": "https://api.github.com/repos/aircrack-ng/aircrack-ng/issues/2565",
                "repository_url": "https://api.github.com/repos/aircrack-ng/aircrack-ng",
                "labels_url": "https://api.github.com/repos/aircrack-ng/aircrack-ng/issues/2565/labels{/name}",
                "comments_url": "https://api.github.com/repos/aircrack-ng/aircrack-ng/issues/2565/comments",
                "events_url": "https://api.github.com/repos/aircrack-ng/aircrack-ng/issues/2565/events",
                "html_url": "https://github.com/aircrack-ng/aircrack-ng/issues/2565",
                "id": 1844101324,
                "node_id": "I_kwDOB25wPM5t6sDM",
                "number": 2565,
                "title": "test-wpapsk-cmac regression on arm64/armhf/armel",
                "user": {
                    "login": "samueloph",
                    "id": 2778482,
                    "node_id": "MDQ6VXNlcjI3Nzg0ODI=",
                    "avatar_url": "https://avatars.githubusercontent.com/u/2778482?v=4",
                    "gravatar_id": "",
                    "url": "https://api.github.com/users/samueloph",
                    "html_url": "https://github.com/samueloph",
                    "followers_url": "https://api.github.com/users/samueloph/followers",
                    "following_url": "https://api.github.com/users/samueloph/following{/other_user}",
                    "gists_url": "https://api.github.com/users/samueloph/gists{/gist_id}",
                    "starred_url": "https://api.github.com/users/samueloph/starred{/owner}{/repo}",
                    "subscriptions_url": "https://api.github.com/users/samueloph/subscriptions",
                    "organizations_url": "https://api.github.com/users/samueloph/orgs",
                    "repos_url": "https://api.github.com/users/samueloph/repos",
                    "events_url": "https://api.github.com/users/samueloph/events{/privacy}",
                    "received_events_url": "https://api.github.com/users/samueloph/received_events",
                    "type": "User",
                    "site_admin": false
                },
                "labels": [],
                "state": "open",
                "locked": false,
                "assignee": null,
                "assignees": [],
                "milestone": null,
                "comments": 3,
                "created_at": "2023-08-09T22:14:48Z",
                "updated_at": "2023-10-20T11:04:39Z",
                "closed_at": null,
                "author_association": "CONTRIBUTOR",
                "active_lock_reason": null,
                "body": "I've recently packaged a git snapshot of aircrack-ng for Debian (at the current HEAD https://github.com/aircrack-ng/aircrack-ng/commit/4bf83f1a7631d6721c17a35597d2f71b35ff30bf), and stumbled upon failures when building for `arm64`/`armhf`/`armel`.\r\n\r\nThe `check` target fails when running the test `test-wpapsk-cmac`.\r\n\r\nI've ran git bisect on the tree and found the commit that introduces the regression:\r\nhttps://github.com/aircrack-ng/aircrack-ng/commit/5e8ed78e8abdb0baf5b78d42e6be4c752b512a35\r\n\r\nLooking at the current open issues/PRs, I can see one that might be related to this issue, but I haven't tested it:\r\nhttps://github.com/aircrack-ng/aircrack-ng/issues/2553\r\nhttps://github.com/aircrack-ng/aircrack-ng/pull/2554\r\n\r\n## Contents of `test-suite.log` (only the important bits)\r\n```\r\nFAIL: test-wpapsk-cmac\r\n======================\r\n\r\n1..2\r\nnot ok 1 - test_crypto_engine_generic\r\n# difference at offset 0 0x97 0x2c\r\n# difference at offset 1 0xd8 0x76\r\n# difference at offset 2 0x90 0xdc\r\n# difference at offset 3 0xb4 0x59\r\n# difference at offset 4 0xfc 0x2c\r\n# difference at offset 5 0x65 0x3b\r\n# difference at offset 6 0xf6 0x67\r\n# difference at offset 7 0x5d 0x1b\r\n# difference at offset 8 0x10 0xac\r\n# difference at offset 9 0xbe 0x23\r\n# difference at offset 10 0x4c 0x0f\r\n# difference at offset 11 0x11 0x6c\r\n# difference at offset 12 0x92 0x9e\r\n# difference at offset 13 0x13 0x38\r\n# difference at offset 14 0x78 0xa0\r\n# difference at offset 15 0x27 0x62\r\n# ...\r\n# 31 bytes of 0xaaab033cf920 and 0xaaaadf5d3f68 differ\r\n# test/unit/test-wpapsk-cmac.c:174: error: Failure!\r\nnot ok 2 - test_crypto_engine_arm_neon\r\n# difference at offset 0 0x97 0x2c\r\n# difference at offset 1 0xd8 0x76\r\n# difference at offset 2 0x90 0xdc\r\n# difference at offset 3 0xb4 0x59\r\n# difference at offset 4 0xfc 0x2c\r\n# difference at offset 5 0x65 0x3b\r\n# difference at offset 6 0xf6 0x67\r\n# difference at offset 7 0x5d 0x1b\r\n# difference at offset 8 0x10 0xac\r\n# difference at offset 9 0xbe 0x23\r\n# difference at offset 10 0x4c 0x0f\r\n# difference at offset 11 0x11 0x6c\r\n# difference at offset 12 0x92 0x9e\r\n# difference at offset 13 0x13 0x38\r\n# difference at offset 14 0x78 0xa0\r\n# difference at offset 15 0x27 0x62\r\n# ...\r\n# 31 bytes of 0xaaab033d29e0 and 0xaaaadf5d3f68 differ\r\n# test/unit/test-wpapsk-cmac.c:174: error: Failure!\r\n# not ok - tests\r\nFAIL test-wpapsk-cmac (exit status: 2)\r\n```\r\n\r\n## Debian build logs\r\nhttps://buildd.debian.org/status/package.php?p=aircrack-ng\r\nhttps://buildd.debian.org/status/fetch.php?pkg=aircrack-ng&arch=arm64&ver=1%3A1.7%2Bgit20230807.4bf83f1a-1&stamp=1691438883&raw=0\r\nhttps://buildd.debian.org/status/fetch.php?pkg=aircrack-ng&arch=armel&ver=1%3A1.7%2Bgit20230807.4bf83f1a-1&stamp=1691439285&raw=0\r\nhttps://buildd.debian.org/status/fetch.php?pkg=aircrack-ng&arch=armhf&ver=1%3A1.7%2Bgit20230807.4bf83f1a-1&stamp=1691439374&raw=0\r\n\r\n## Script used to bisect\r\n```\r\n#!/bin/bash\r\n\r\nuntestable() {\r\n    git reset --hard\r\n    exit 125\r\n}\r\n\r\nfail() {\r\n    git reset --hard\r\n    exit 1\r\n}\r\n\r\nautoreconf -fiv || untestable\r\n./configure \\\r\n    --with-gcrypt \\\r\n    --with-experimental || untestable\r\n\r\nmake -j4 || untestable\r\n\r\n# Apply https://github.com/aircrack-ng/aircrack-ng/pull/2563 to\r\n# add missing import.\r\nsed -i '1s/^/#include <inttypes.h>\\n/' src/airodump-ng/airodump-ng.c || untestable\r\n\r\n# Modify makefile to only run test-wpapsk-cmac on make check.\r\nsed -i -e \"s|#am__append_1 = -liphlpapi -lsetupapi|check_PROGRAMS =  \\$(am__EXEEXT_5)\\nTESTS = \\$(am__EXEEXT_5)\\n#am__append_1 = -liphlpapi -lsetupapi|g\" Makefile || untestable\r\n\r\n# Run tests a few times to not get tricked by an issue that\r\n# might only show up on some runs (due to parallelism).\r\nmake -j4 check || fail\r\ntouch test/unit/test-wpapsk-cmac.c\r\nmake -j4 check || fail\r\ntouch test/unit/test-wpapsk-cmac.c\r\nmake -j4 check || fail\r\ntouch test/unit/test-wpapsk-cmac.c\r\nmake -j4 check || fail\r\ntouch test/unit/test-wpapsk-cmac.c\r\nmake -j4 check || fail\r\ntouch test/unit/test-wpapsk-cmac.c\r\n\r\n# If we got here, success.\r\ngit reset --hard\r\nexit 0\r\n```",
                "reactions": {
                    "url": "https://api.github.com/repos/aircrack-ng/aircrack-ng/issues/2565/reactions",
                    "total_count": 0,
                    "+1": 0,
                    "-1": 0,
                    "laugh": 0,
                    "hooray": 0,
                    "confused": 0,
                    "heart": 0,
                    "rocket": 0,
                    "eyes": 0
                },
                "timeline_url": "https://api.github.com/repos/aircrack-ng/aircrack-ng/issues/2565/timeline",
                "performed_via_github_app": null,
                "state_reason": null
            },
            "comment": {
                "url": "https://api.github.com/repos/aircrack-ng/aircrack-ng/issues/comments/1772537109",
                "html_url": "https://github.com/aircrack-ng/aircrack-ng/issues/2565#issuecomment-1772537109",
                "issue_url": "https://api.github.com/repos/aircrack-ng/aircrack-ng/issues/2565",
                "id": 1772537109,
                "node_id": "IC_kwDOB25wPM5ppsUV",
                "user": {
                    "login": "bdrung",
                    "id": 239485,
                    "node_id": "MDQ6VXNlcjIzOTQ4NQ==",
                    "avatar_url": "https://avatars.githubusercontent.com/u/239485?v=4",
                    "gravatar_id": "",
                    "url": "https://api.github.com/users/bdrung",
                    "html_url": "https://github.com/bdrung",
                    "followers_url": "https://api.github.com/users/bdrung/followers",
                    "following_url": "https://api.github.com/users/bdrung/following{/other_user}",
                    "gists_url": "https://api.github.com/users/bdrung/gists{/gist_id}",
                    "starred_url": "https://api.github.com/users/bdrung/starred{/owner}{/repo}",
                    "subscriptions_url": "https://api.github.com/users/bdrung/subscriptions",
                    "organizations_url": "https://api.github.com/users/bdrung/orgs",
                    "repos_url": "https://api.github.com/users/bdrung/repos",
                    "events_url": "https://api.github.com/users/bdrung/events{/privacy}",
                    "received_events_url": "https://api.github.com/users/bdrung/received_events",
                    "type": "User",
                    "site_admin": false
                },
                "created_at": "2023-10-20T11:04:38Z",
                "updated_at": "2023-10-20T11:04:38Z",
                "author_association": "NONE",
                "body": "The failure can also be seen on Ubuntu: https://bugs.launchpad.net/ubuntu/+source/aircrack-ng/+bug/2039967",
                "reactions": {
                    "url": "https://api.github.com/repos/aircrack-ng/aircrack-ng/issues/comments/1772537109/reactions",
                    "total_count": 0,
                    "+1": 0,
                    "-1": 0,
                    "laugh": 0,
                    "hooray": 0,
                    "confused": 0,
                    "heart": 0,
                    "rocket": 0,
                    "eyes": 0
                },
                "performed_via_github_app": null
            }
        },
        "public": true,
        "created_at": "2023-10-20T11:04:39Z"
    },
    {
        "id": "32703392373",
        "type": "WatchEvent",
        "actor": {
            "id": 121355376,
            "login": "Dvbvdo710",
            "display_login": "Dvbvdo710",
            "gravatar_id": "",
            "url": "https://api.github.com/users/Dvbvdo710",
            "avatar_url": "https://avatars.githubusercontent.com/u/121355376?"
        },
        "repo": {
            "id": 124678204,
            "name": "aircrack-ng/aircrack-ng",
            "url": "https://api.github.com/repos/aircrack-ng/aircrack-ng"
        },
        "payload": {
            "action": "started"
        },
        "public": true,
        "created_at": "2023-10-19T20:06:41Z"
    },
    {
        "id": "32698645466",
        "type": "PullRequestEvent",
        "actor": {
            "id": 3667366,
            "login": "garsaud",
            "display_login": "garsaud",
            "gravatar_id": "",
            "url": "https://api.github.com/users/garsaud",
            "avatar_url": "https://avatars.githubusercontent.com/u/3667366?"
        },
        "repo": {
            "id": 124678204,
            "name": "aircrack-ng/aircrack-ng",
            "url": "https://api.github.com/repos/aircrack-ng/aircrack-ng"
        },
        "payload": {
            "action": "opened",
            "number": 2586,
            "pull_request": {
                "url": "https://api.github.com/repos/aircrack-ng/aircrack-ng/pulls/2586",
                "id": 1565258215,
                "node_id": "PR_kwDOB25wPM5dS_Hn",
                "html_url": "https://github.com/aircrack-ng/aircrack-ng/pull/2586",
                "diff_url": "https://github.com/aircrack-ng/aircrack-ng/pull/2586.diff",
                "patch_url": "https://github.com/aircrack-ng/aircrack-ng/pull/2586.patch",
                "issue_url": "https://api.github.com/repos/aircrack-ng/aircrack-ng/issues/2586",
                "number": 2586,
                "state": "open",
                "locked": false,
                "title": "Fix quitting aircrack-ng using CTRL+C",
                "user": {
                    "login": "garsaud",
                    "id": 3667366,
                    "node_id": "MDQ6VXNlcjM2NjczNjY=",
                    "avatar_url": "https://avatars.githubusercontent.com/u/3667366?v=4",
                    "gravatar_id": "",
                    "url": "https://api.github.com/users/garsaud",
                    "html_url": "https://github.com/garsaud",
                    "followers_url": "https://api.github.com/users/garsaud/followers",
                    "following_url": "https://api.github.com/users/garsaud/following{/other_user}",
                    "gists_url": "https://api.github.com/users/garsaud/gists{/gist_id}",
                    "starred_url": "https://api.github.com/users/garsaud/starred{/owner}{/repo}",
                    "subscriptions_url": "https://api.github.com/users/garsaud/subscriptions",
                    "organizations_url": "https://api.github.com/users/garsaud/orgs",
                    "repos_url": "https://api.github.com/users/garsaud/repos",
                    "events_url": "https://api.github.com/users/garsaud/events{/privacy}",
                    "received_events_url": "https://api.github.com/users/garsaud/received_events",
                    "type": "User",
                    "site_admin": false
                },
                "body": "Fixes issue #2585\r\n\r\nAllow for a user to quit while Aircrack prompts for a target.\r\n\r\nResult:\r\n<img width=\"623\" alt=\"Screenshot of aircrack successfully closed using ctrl+c\" src=\"https://github.com/aircrack-ng/aircrack-ng/assets/3667366/590ddbf4-38d3-44b1-bc09-e758647490fd\">",
                "created_at": "2023-10-19T16:45:36Z",
                "updated_at": "2023-10-19T16:45:36Z",
                "closed_at": null,
                "merged_at": null,
                "merge_commit_sha": null,
                "assignee": null,
                "assignees": [],
                "requested_reviewers": [],
                "requested_teams": [],
                "labels": [],
                "milestone": null,
                "draft": false,
                "commits_url": "https://api.github.com/repos/aircrack-ng/aircrack-ng/pulls/2586/commits",
                "review_comments_url": "https://api.github.com/repos/aircrack-ng/aircrack-ng/pulls/2586/comments",
                "review_comment_url": "https://api.github.com/repos/aircrack-ng/aircrack-ng/pulls/comments{/number}",
                "comments_url": "https://api.github.com/repos/aircrack-ng/aircrack-ng/issues/2586/comments",
                "statuses_url": "https://api.github.com/repos/aircrack-ng/aircrack-ng/statuses/ba8567e6927a534307feeda90e5dfde5f0070cd2",
                "head": {
                    "label": "garsaud:patch-1",
                    "ref": "patch-1",
                    "sha": "ba8567e6927a534307feeda90e5dfde5f0070cd2",
                    "user": {
                        "login": "garsaud",
                        "id": 3667366,
                        "node_id": "MDQ6VXNlcjM2NjczNjY=",
                        "avatar_url": "https://avatars.githubusercontent.com/u/3667366?v=4",
                        "gravatar_id": "",
                        "url": "https://api.github.com/users/garsaud",
                        "html_url": "https://github.com/garsaud",
                        "followers_url": "https://api.github.com/users/garsaud/followers",
                        "following_url": "https://api.github.com/users/garsaud/following{/other_user}",
                        "gists_url": "https://api.github.com/users/garsaud/gists{/gist_id}",
                        "starred_url": "https://api.github.com/users/garsaud/starred{/owner}{/repo}",
                        "subscriptions_url": "https://api.github.com/users/garsaud/subscriptions",
                        "organizations_url": "https://api.github.com/users/garsaud/orgs",
                        "repos_url": "https://api.github.com/users/garsaud/repos",
                        "events_url": "https://api.github.com/users/garsaud/events{/privacy}",
                        "received_events_url": "https://api.github.com/users/garsaud/received_events",
                        "type": "User",
                        "site_admin": false
                    },
                    "repo": {
                        "id": 707291015,
                        "node_id": "R_kgDOKihnhw",
                        "name": "aircrack-ng",
                        "full_name": "garsaud/aircrack-ng",
                        "private": false,
                        "owner": {
                            "login": "garsaud",
                            "id": 3667366,
                            "node_id": "MDQ6VXNlcjM2NjczNjY=",
                            "avatar_url": "https://avatars.githubusercontent.com/u/3667366?v=4",
                            "gravatar_id": "",
                            "url": "https://api.github.com/users/garsaud",
                            "html_url": "https://github.com/garsaud",
                            "followers_url": "https://api.github.com/users/garsaud/followers",
                            "following_url": "https://api.github.com/users/garsaud/following{/other_user}",
                            "gists_url": "https://api.github.com/users/garsaud/gists{/gist_id}",
                            "starred_url": "https://api.github.com/users/garsaud/starred{/owner}{/repo}",
                            "subscriptions_url": "https://api.github.com/users/garsaud/subscriptions",
                            "organizations_url": "https://api.github.com/users/garsaud/orgs",
                            "repos_url": "https://api.github.com/users/garsaud/repos",
                            "events_url": "https://api.github.com/users/garsaud/events{/privacy}",
                            "received_events_url": "https://api.github.com/users/garsaud/received_events",
                            "type": "User",
                            "site_admin": false
                        },
                        "html_url": "https://github.com/garsaud/aircrack-ng",
                        "description": "WiFi security auditing tools suite",
                        "fork": true,
                        "url": "https://api.github.com/repos/garsaud/aircrack-ng",
                        "forks_url": "https://api.github.com/repos/garsaud/aircrack-ng/forks",
                        "keys_url": "https://api.github.com/repos/garsaud/aircrack-ng/keys{/key_id}",
                        "collaborators_url": "https://api.github.com/repos/garsaud/aircrack-ng/collaborators{/collaborator}",
                        "teams_url": "https://api.github.com/repos/garsaud/aircrack-ng/teams",
                        "hooks_url": "https://api.github.com/repos/garsaud/aircrack-ng/hooks",
                        "issue_events_url": "https://api.github.com/repos/garsaud/aircrack-ng/issues/events{/number}",
                        "events_url": "https://api.github.com/repos/garsaud/aircrack-ng/events",
                        "assignees_url": "https://api.github.com/repos/garsaud/aircrack-ng/assignees{/user}",
                        "branches_url": "https://api.github.com/repos/garsaud/aircrack-ng/branches{/branch}",
                        "tags_url": "https://api.github.com/repos/garsaud/aircrack-ng/tags",
                        "blobs_url": "https://api.github.com/repos/garsaud/aircrack-ng/git/blobs{/sha}",
                        "git_tags_url": "https://api.github.com/repos/garsaud/aircrack-ng/git/tags{/sha}",
                        "git_refs_url": "https://api.github.com/repos/garsaud/aircrack-ng/git/refs{/sha}",
                        "trees_url": "https://api.github.com/repos/garsaud/aircrack-ng/git/trees{/sha}",
                        "statuses_url": "https://api.github.com/repos/garsaud/aircrack-ng/statuses/{sha}",
                        "languages_url": "https://api.github.com/repos/garsaud/aircrack-ng/languages",
                        "stargazers_url": "https://api.github.com/repos/garsaud/aircrack-ng/stargazers",
                        "contributors_url": "https://api.github.com/repos/garsaud/aircrack-ng/contributors",
                        "subscribers_url": "https://api.github.com/repos/garsaud/aircrack-ng/subscribers",
                        "subscription_url": "https://api.github.com/repos/garsaud/aircrack-ng/subscription",
                        "commits_url": "https://api.github.com/repos/garsaud/aircrack-ng/commits{/sha}",
                        "git_commits_url": "https://api.github.com/repos/garsaud/aircrack-ng/git/commits{/sha}",
                        "comments_url": "https://api.github.com/repos/garsaud/aircrack-ng/comments{/number}",
                        "issue_comment_url": "https://api.github.com/repos/garsaud/aircrack-ng/issues/comments{/number}",
                        "contents_url": "https://api.github.com/repos/garsaud/aircrack-ng/contents/{+path}",
                        "compare_url": "https://api.github.com/repos/garsaud/aircrack-ng/compare/{base}...{head}",
                        "merges_url": "https://api.github.com/repos/garsaud/aircrack-ng/merges",
                        "archive_url": "https://api.github.com/repos/garsaud/aircrack-ng/{archive_format}{/ref}",
                        "downloads_url": "https://api.github.com/repos/garsaud/aircrack-ng/downloads",
                        "issues_url": "https://api.github.com/repos/garsaud/aircrack-ng/issues{/number}",
                        "pulls_url": "https://api.github.com/repos/garsaud/aircrack-ng/pulls{/number}",
                        "milestones_url": "https://api.github.com/repos/garsaud/aircrack-ng/milestones{/number}",
                        "notifications_url": "https://api.github.com/repos/garsaud/aircrack-ng/notifications{?since,all,participating}",
                        "labels_url": "https://api.github.com/repos/garsaud/aircrack-ng/labels{/name}",
                        "releases_url": "https://api.github.com/repos/garsaud/aircrack-ng/releases{/id}",
                        "deployments_url": "https://api.github.com/repos/garsaud/aircrack-ng/deployments",
                        "created_at": "2023-10-19T15:40:38Z",
                        "updated_at": "2023-10-19T15:40:38Z",
                        "pushed_at": "2023-10-19T15:54:52Z",
                        "git_url": "git://github.com/garsaud/aircrack-ng.git",
                        "ssh_url": "git@github.com:garsaud/aircrack-ng.git",
                        "clone_url": "https://github.com/garsaud/aircrack-ng.git",
                        "svn_url": "https://github.com/garsaud/aircrack-ng",
                        "homepage": "https://aircrack-ng.org",
                        "size": 16872,
                        "stargazers_count": 0,
                        "watchers_count": 0,
                        "language": null,
                        "has_issues": false,
                        "has_projects": true,
                        "has_downloads": true,
                        "has_wiki": false,
                        "has_pages": false,
                        "has_discussions": false,
                        "forks_count": 0,
                        "mirror_url": null,
                        "archived": false,
                        "disabled": false,
                        "open_issues_count": 0,
                        "license": {
                            "key": "gpl-2.0",
                            "name": "GNU General Public License v2.0",
                            "spdx_id": "GPL-2.0",
                            "url": "https://api.github.com/licenses/gpl-2.0",
                            "node_id": "MDc6TGljZW5zZTg="
                        },
                        "allow_forking": true,
                        "is_template": false,
                        "web_commit_signoff_required": false,
                        "topics": [],
                        "visibility": "public",
                        "forks": 0,
                        "open_issues": 0,
                        "watchers": 0,
                        "default_branch": "master"
                    }
                },
                "base": {
                    "label": "aircrack-ng:master",
                    "ref": "master",
                    "sha": "e82138cbd5e227a8d4dcbb6268cbeff5712d9774",
                    "user": {
                        "login": "aircrack-ng",
                        "id": 4042925,
                        "node_id": "MDQ6VXNlcjQwNDI5MjU=",
                        "avatar_url": "https://avatars.githubusercontent.com/u/4042925?v=4",
                        "gravatar_id": "",
                        "url": "https://api.github.com/users/aircrack-ng",
                        "html_url": "https://github.com/aircrack-ng",
                        "followers_url": "https://api.github.com/users/aircrack-ng/followers",
                        "following_url": "https://api.github.com/users/aircrack-ng/following{/other_user}",
                        "gists_url": "https://api.github.com/users/aircrack-ng/gists{/gist_id}",
                        "starred_url": "https://api.github.com/users/aircrack-ng/starred{/owner}{/repo}",
                        "subscriptions_url": "https://api.github.com/users/aircrack-ng/subscriptions",
                        "organizations_url": "https://api.github.com/users/aircrack-ng/orgs",
                        "repos_url": "https://api.github.com/users/aircrack-ng/repos",
                        "events_url": "https://api.github.com/users/aircrack-ng/events{/privacy}",
                        "received_events_url": "https://api.github.com/users/aircrack-ng/received_events",
                        "type": "User",
                        "site_admin": false
                    },
                    "repo": {
                        "id": 124678204,
                        "node_id": "MDEwOlJlcG9zaXRvcnkxMjQ2NzgyMDQ=",
                        "name": "aircrack-ng",
                        "full_name": "aircrack-ng/aircrack-ng",
                        "private": false,
                        "owner": {
                            "login": "aircrack-ng",
                            "id": 4042925,
                            "node_id": "MDQ6VXNlcjQwNDI5MjU=",
                            "avatar_url": "https://avatars.githubusercontent.com/u/4042925?v=4",
                            "gravatar_id": "",
                            "url": "https://api.github.com/users/aircrack-ng",
                            "html_url": "https://github.com/aircrack-ng",
                            "followers_url": "https://api.github.com/users/aircrack-ng/followers",
                            "following_url": "https://api.github.com/users/aircrack-ng/following{/other_user}",
                            "gists_url": "https://api.github.com/users/aircrack-ng/gists{/gist_id}",
                            "starred_url": "https://api.github.com/users/aircrack-ng/starred{/owner}{/repo}",
                            "subscriptions_url": "https://api.github.com/users/aircrack-ng/subscriptions",
                            "organizations_url": "https://api.github.com/users/aircrack-ng/orgs",
                            "repos_url": "https://api.github.com/users/aircrack-ng/repos",
                            "events_url": "https://api.github.com/users/aircrack-ng/events{/privacy}",
                            "received_events_url": "https://api.github.com/users/aircrack-ng/received_events",
                            "type": "User",
                            "site_admin": false
                        },
                        "html_url": "https://github.com/aircrack-ng/aircrack-ng",
                        "description": "WiFi security auditing tools suite",
                        "fork": false,
                        "url": "https://api.github.com/repos/aircrack-ng/aircrack-ng",
                        "forks_url": "https://api.github.com/repos/aircrack-ng/aircrack-ng/forks",
                        "keys_url": "https://api.github.com/repos/aircrack-ng/aircrack-ng/keys{/key_id}",
                        "collaborators_url": "https://api.github.com/repos/aircrack-ng/aircrack-ng/collaborators{/collaborator}",
                        "teams_url": "https://api.github.com/repos/aircrack-ng/aircrack-ng/teams",
                        "hooks_url": "https://api.github.com/repos/aircrack-ng/aircrack-ng/hooks",
                        "issue_events_url": "https://api.github.com/repos/aircrack-ng/aircrack-ng/issues/events{/number}",
                        "events_url": "https://api.github.com/repos/aircrack-ng/aircrack-ng/events",
                        "assignees_url": "https://api.github.com/repos/aircrack-ng/aircrack-ng/assignees{/user}",
                        "branches_url": "https://api.github.com/repos/aircrack-ng/aircrack-ng/branches{/branch}",
                        "tags_url": "https://api.github.com/repos/aircrack-ng/aircrack-ng/tags",
                        "blobs_url": "https://api.github.com/repos/aircrack-ng/aircrack-ng/git/blobs{/sha}",
                        "git_tags_url": "https://api.github.com/repos/aircrack-ng/aircrack-ng/git/tags{/sha}",
                        "git_refs_url": "https://api.github.com/repos/aircrack-ng/aircrack-ng/git/refs{/sha}",
                        "trees_url": "https://api.github.com/repos/aircrack-ng/aircrack-ng/git/trees{/sha}",
                        "statuses_url": "https://api.github.com/repos/aircrack-ng/aircrack-ng/statuses/{sha}",
                        "languages_url": "https://api.github.com/repos/aircrack-ng/aircrack-ng/languages",
                        "stargazers_url": "https://api.github.com/repos/aircrack-ng/aircrack-ng/stargazers",
                        "contributors_url": "https://api.github.com/repos/aircrack-ng/aircrack-ng/contributors",
                        "subscribers_url": "https://api.github.com/repos/aircrack-ng/aircrack-ng/subscribers",
                        "subscription_url": "https://api.github.com/repos/aircrack-ng/aircrack-ng/subscription",
                        "commits_url": "https://api.github.com/repos/aircrack-ng/aircrack-ng/commits{/sha}",
                        "git_commits_url": "https://api.github.com/repos/aircrack-ng/aircrack-ng/git/commits{/sha}",
                        "comments_url": "https://api.github.com/repos/aircrack-ng/aircrack-ng/comments{/number}",
                        "issue_comment_url": "https://api.github.com/repos/aircrack-ng/aircrack-ng/issues/comments{/number}",
                        "contents_url": "https://api.github.com/repos/aircrack-ng/aircrack-ng/contents/{+path}",
                        "compare_url": "https://api.github.com/repos/aircrack-ng/aircrack-ng/compare/{base}...{head}",
                        "merges_url": "https://api.github.com/repos/aircrack-ng/aircrack-ng/merges",
                        "archive_url": "https://api.github.com/repos/aircrack-ng/aircrack-ng/{archive_format}{/ref}",
                        "downloads_url": "https://api.github.com/repos/aircrack-ng/aircrack-ng/downloads",
                        "issues_url": "https://api.github.com/repos/aircrack-ng/aircrack-ng/issues{/number}",
                        "pulls_url": "https://api.github.com/repos/aircrack-ng/aircrack-ng/pulls{/number}",
                        "milestones_url": "https://api.github.com/repos/aircrack-ng/aircrack-ng/milestones{/number}",
                        "notifications_url": "https://api.github.com/repos/aircrack-ng/aircrack-ng/notifications{?since,all,participating}",
                        "labels_url": "https://api.github.com/repos/aircrack-ng/aircrack-ng/labels{/name}",
                        "releases_url": "https://api.github.com/repos/aircrack-ng/aircrack-ng/releases{/id}",
                        "deployments_url": "https://api.github.com/repos/aircrack-ng/aircrack-ng/deployments",
                        "created_at": "2018-03-10T17:11:11Z",
                        "updated_at": "2023-10-19T13:18:44Z",
                        "pushed_at": "2023-10-19T16:45:37Z",
                        "git_url": "git://github.com/aircrack-ng/aircrack-ng.git",
                        "ssh_url": "git@github.com:aircrack-ng/aircrack-ng.git",
                        "clone_url": "https://github.com/aircrack-ng/aircrack-ng.git",
                        "svn_url": "https://github.com/aircrack-ng/aircrack-ng",
                        "homepage": "https://aircrack-ng.org",
                        "size": 16872,
                        "stargazers_count": 4280,
                        "watchers_count": 4280,
                        "language": "C",
                        "has_issues": true,
                        "has_projects": false,
                        "has_downloads": true,
                        "has_wiki": false,
                        "has_pages": false,
                        "has_discussions": true,
                        "forks_count": 843,
                        "mirror_url": null,
                        "archived": false,
                        "disabled": false,
                        "open_issues_count": 414,
                        "license": {
                            "key": "gpl-2.0",
                            "name": "GNU General Public License v2.0",
                            "spdx_id": "GPL-2.0",
                            "url": "https://api.github.com/licenses/gpl-2.0",
                            "node_id": "MDc6TGljZW5zZTg="
                        },
                        "allow_forking": true,
                        "is_template": false,
                        "web_commit_signoff_required": false,
                        "topics": [
                            "audit",
                            "freeradius",
                            "hostapd",
                            "security",
                            "suite",
                            "wifi",
                            "wifi-security"
                        ],
                        "visibility": "public",
                        "forks": 843,
                        "open_issues": 414,
                        "watchers": 4280,
                        "default_branch": "master"
                    }
                },
                "_links": {
                    "self": {
                        "href": "https://api.github.com/repos/aircrack-ng/aircrack-ng/pulls/2586"
                    },
                    "html": {
                        "href": "https://github.com/aircrack-ng/aircrack-ng/pull/2586"
                    },
                    "issue": {
                        "href": "https://api.github.com/repos/aircrack-ng/aircrack-ng/issues/2586"
                    },
                    "comments": {
                        "href": "https://api.github.com/repos/aircrack-ng/aircrack-ng/issues/2586/comments"
                    },
                    "review_comments": {
                        "href": "https://api.github.com/repos/aircrack-ng/aircrack-ng/pulls/2586/comments"
                    },
                    "review_comment": {
                        "href": "https://api.github.com/repos/aircrack-ng/aircrack-ng/pulls/comments{/number}"
                    },
                    "commits": {
                        "href": "https://api.github.com/repos/aircrack-ng/aircrack-ng/pulls/2586/commits"
                    },
                    "statuses": {
                        "href": "https://api.github.com/repos/aircrack-ng/aircrack-ng/statuses/ba8567e6927a534307feeda90e5dfde5f0070cd2"
                    }
                },
                "author_association": "NONE",
                "auto_merge": null,
                "active_lock_reason": null,
                "merged": false,
                "mergeable": null,
                "rebaseable": null,
                "mergeable_state": "unknown",
                "merged_by": null,
                "comments": 0,
                "review_comments": 0,
                "maintainer_can_modify": true,
                "commits": 1,
                "additions": 6,
                "deletions": 4,
                "changed_files": 1
            }
        },
        "public": true,
        "created_at": "2023-10-19T16:45:38Z"
    }
]