[
    {
        "id": "32896697910",
        "type": "WatchEvent",
        "actor": {
            "id": 95097635,
            "login": "A-caibird",
            "display_login": "A-caibird",
            "gravatar_id": "",
            "url": "https://api.github.com/users/A-caibird",
            "avatar_url": "https://avatars.githubusercontent.com/u/95097635?"
        },
        "repo": {
            "id": 77213120,
            "name": "Eugeny/tabby",
            "url": "https://api.github.com/repos/Eugeny/tabby"
        },
        "payload": {
            "action": "started"
        },
        "public": true,
        "created_at": "2023-10-27T11:11:11Z"
    },
    {
        "id": "32896212921",
        "type": "WatchEvent",
        "actor": {
            "id": 14094437,
            "login": "Peng-GXP",
            "display_login": "Peng-GXP",
            "gravatar_id": "",
            "url": "https://api.github.com/users/Peng-GXP",
            "avatar_url": "https://avatars.githubusercontent.com/u/14094437?"
        },
        "repo": {
            "id": 77213120,
            "name": "Eugeny/tabby",
            "url": "https://api.github.com/repos/Eugeny/tabby"
        },
        "payload": {
            "action": "started"
        },
        "public": true,
        "created_at": "2023-10-27T10:51:07Z"
    },
    {
        "id": "32895852865",
        "type": "WatchEvent",
        "actor": {
            "id": 70734012,
            "login": "AllenZenghuge",
            "display_login": "AllenZenghuge",
            "gravatar_id": "",
            "url": "https://api.github.com/users/AllenZenghuge",
            "avatar_url": "https://avatars.githubusercontent.com/u/70734012?"
        },
        "repo": {
            "id": 77213120,
            "name": "Eugeny/tabby",
            "url": "https://api.github.com/repos/Eugeny/tabby"
        },
        "payload": {
            "action": "started"
        },
        "public": true,
        "created_at": "2023-10-27T10:35:58Z"
    },
    {
        "id": "32895797095",
        "type": "WatchEvent",
        "actor": {
            "id": 99661139,
            "login": "jan-rodson",
            "display_login": "jan-rodson",
            "gravatar_id": "",
            "url": "https://api.github.com/users/jan-rodson",
            "avatar_url": "https://avatars.githubusercontent.com/u/99661139?"
        },
        "repo": {
            "id": 77213120,
            "name": "Eugeny/tabby",
            "url": "https://api.github.com/repos/Eugeny/tabby"
        },
        "payload": {
            "action": "started"
        },
        "public": true,
        "created_at": "2023-10-27T10:33:40Z"
    },
    {
        "id": "32894335734",
        "type": "WatchEvent",
        "actor": {
            "id": 62000745,
            "login": "soundofautumn",
            "display_login": "soundofautumn",
            "gravatar_id": "",
            "url": "https://api.github.com/users/soundofautumn",
            "avatar_url": "https://avatars.githubusercontent.com/u/62000745?"
        },
        "repo": {
            "id": 77213120,
            "name": "Eugeny/tabby",
            "url": "https://api.github.com/repos/Eugeny/tabby"
        },
        "payload": {
            "action": "started"
        },
        "public": true,
        "created_at": "2023-10-27T09:38:07Z"
    },
    {
        "id": "32893611313",
        "type": "WatchEvent",
        "actor": {
            "id": 40118676,
            "login": "customtea",
            "display_login": "customtea",
            "gravatar_id": "",
            "url": "https://api.github.com/users/customtea",
            "avatar_url": "https://avatars.githubusercontent.com/u/40118676?"
        },
        "repo": {
            "id": 77213120,
            "name": "Eugeny/tabby",
            "url": "https://api.github.com/repos/Eugeny/tabby"
        },
        "payload": {
            "action": "started"
        },
        "public": true,
        "created_at": "2023-10-27T09:10:56Z"
    },
    {
        "id": "32893400349",
        "type": "WatchEvent",
        "actor": {
            "id": 49568859,
            "login": "sdpigpig",
            "display_login": "sdpigpig",
            "gravatar_id": "",
            "url": "https://api.github.com/users/sdpigpig",
            "avatar_url": "https://avatars.githubusercontent.com/u/49568859?"
        },
        "repo": {
            "id": 77213120,
            "name": "Eugeny/tabby",
            "url": "https://api.github.com/repos/Eugeny/tabby"
        },
        "payload": {
            "action": "started"
        },
        "public": true,
        "created_at": "2023-10-27T09:02:58Z"
    },
    {
        "id": "32892850805",
        "type": "WatchEvent",
        "actor": {
            "id": 2038316,
            "login": "liurenqiu520",
            "display_login": "liurenqiu520",
            "gravatar_id": "",
            "url": "https://api.github.com/users/liurenqiu520",
            "avatar_url": "https://avatars.githubusercontent.com/u/2038316?"
        },
        "repo": {
            "id": 77213120,
            "name": "Eugeny/tabby",
            "url": "https://api.github.com/repos/Eugeny/tabby"
        },
        "payload": {
            "action": "started"
        },
        "public": true,
        "created_at": "2023-10-27T08:42:14Z"
    },
    {
        "id": "32892531631",
        "type": "WatchEvent",
        "actor": {
            "id": 4082111,
            "login": "imhun",
            "display_login": "imhun",
            "gravatar_id": "",
            "url": "https://api.github.com/users/imhun",
            "avatar_url": "https://avatars.githubusercontent.com/u/4082111?"
        },
        "repo": {
            "id": 77213120,
            "name": "Eugeny/tabby",
            "url": "https://api.github.com/repos/Eugeny/tabby"
        },
        "payload": {
            "action": "started"
        },
        "public": true,
        "created_at": "2023-10-27T08:29:53Z"
    },
    {
        "id": "32890975092",
        "type": "WatchEvent",
        "actor": {
            "id": 56161102,
            "login": "browneyedsoul",
            "display_login": "browneyedsoul",
            "gravatar_id": "",
            "url": "https://api.github.com/users/browneyedsoul",
            "avatar_url": "https://avatars.githubusercontent.com/u/56161102?"
        },
        "repo": {
            "id": 77213120,
            "name": "Eugeny/tabby",
            "url": "https://api.github.com/repos/Eugeny/tabby"
        },
        "payload": {
            "action": "started"
        },
        "public": true,
        "created_at": "2023-10-27T07:26:41Z"
    },
    {
        "id": "32890685124",
        "type": "IssuesEvent",
        "actor": {
            "id": 14366592,
            "login": "lulzhipsters",
            "display_login": "lulzhipsters",
            "gravatar_id": "",
            "url": "https://api.github.com/users/lulzhipsters",
            "avatar_url": "https://avatars.githubusercontent.com/u/14366592?"
        },
        "repo": {
            "id": 77213120,
            "name": "Eugeny/tabby",
            "url": "https://api.github.com/repos/Eugeny/tabby"
        },
        "payload": {
            "action": "opened",
            "issue": {
                "url": "https://api.github.com/repos/Eugeny/tabby/issues/9176",
                "repository_url": "https://api.github.com/repos/Eugeny/tabby",
                "labels_url": "https://api.github.com/repos/Eugeny/tabby/issues/9176/labels{/name}",
                "comments_url": "https://api.github.com/repos/Eugeny/tabby/issues/9176/comments",
                "events_url": "https://api.github.com/repos/Eugeny/tabby/issues/9176/events",
                "html_url": "https://github.com/Eugeny/tabby/issues/9176",
                "id": 1964911208,
                "node_id": "I_kwDOBJotwM51Hipo",
                "number": 9176,
                "title": "Powershell - extra characters are added unexpectedly",
                "user": {
                    "login": "lulzhipsters",
                    "id": 14366592,
                    "node_id": "MDQ6VXNlcjE0MzY2NTky",
                    "avatar_url": "https://avatars.githubusercontent.com/u/14366592?v=4",
                    "gravatar_id": "",
                    "url": "https://api.github.com/users/lulzhipsters",
                    "html_url": "https://github.com/lulzhipsters",
                    "followers_url": "https://api.github.com/users/lulzhipsters/followers",
                    "following_url": "https://api.github.com/users/lulzhipsters/following{/other_user}",
                    "gists_url": "https://api.github.com/users/lulzhipsters/gists{/gist_id}",
                    "starred_url": "https://api.github.com/users/lulzhipsters/starred{/owner}{/repo}",
                    "subscriptions_url": "https://api.github.com/users/lulzhipsters/subscriptions",
                    "organizations_url": "https://api.github.com/users/lulzhipsters/orgs",
                    "repos_url": "https://api.github.com/users/lulzhipsters/repos",
                    "events_url": "https://api.github.com/users/lulzhipsters/events{/privacy}",
                    "received_events_url": "https://api.github.com/users/lulzhipsters/received_events",
                    "type": "User",
                    "site_admin": false
                },
                "labels": [],
                "state": "open",
                "locked": false,
                "assignee": null,
                "assignees": [],
                "milestone": null,
                "comments": 0,
                "created_at": "2023-10-27T07:13:59Z",
                "updated_at": "2023-10-27T07:13:59Z",
                "closed_at": null,
                "author_association": "NONE",
                "active_lock_reason": null,
                "body": "Version: 1.0.201\r\nPlatform: Windows x64 10.0.19045\r\nPlugins: none\r\nFrontend: xterm-webgl\r\n\r\nWhen moving the cursor right-to-left over existing text, `[D` sequences are inserted sporadically:\r\n![image](https://github.com/Eugeny/tabby/assets/14366592/4d439fce-3e94-4aad-80b1-d1d052efdd33)",
                "reactions": {
                    "url": "https://api.github.com/repos/Eugeny/tabby/issues/9176/reactions",
                    "total_count": 0,
                    "+1": 0,
                    "-1": 0,
                    "laugh": 0,
                    "hooray": 0,
                    "confused": 0,
                    "heart": 0,
                    "rocket": 0,
                    "eyes": 0
                },
                "timeline_url": "https://api.github.com/repos/Eugeny/tabby/issues/9176/timeline",
                "performed_via_github_app": null,
                "state_reason": null
            }
        },
        "public": true,
        "created_at": "2023-10-27T07:14:01Z"
    },
    {
        "id": "32890670562",
        "type": "IssueCommentEvent",
        "actor": {
            "id": 14366592,
            "login": "lulzhipsters",
            "display_login": "lulzhipsters",
            "gravatar_id": "",
            "url": "https://api.github.com/users/lulzhipsters",
            "avatar_url": "https://avatars.githubusercontent.com/u/14366592?"
        },
        "repo": {
            "id": 77213120,
            "name": "Eugeny/tabby",
            "url": "https://api.github.com/repos/Eugeny/tabby"
        },
        "payload": {
            "action": "created",
            "issue": {
                "url": "https://api.github.com/repos/Eugeny/tabby/issues/6930",
                "repository_url": "https://api.github.com/repos/Eugeny/tabby",
                "labels_url": "https://api.github.com/repos/Eugeny/tabby/issues/6930/labels{/name}",
                "comments_url": "https://api.github.com/repos/Eugeny/tabby/issues/6930/comments",
                "events_url": "https://api.github.com/repos/Eugeny/tabby/issues/6930/events",
                "html_url": "https://github.com/Eugeny/tabby/issues/6930",
                "id": 1330148801,
                "node_id": "I_kwDOBJotwM5PSHXB",
                "number": 6930,
                "title": "PowerShell automatically adding current directory to function parameters during function calls",
                "user": {
                    "login": "fischgeek",
                    "id": 4293840,
                    "node_id": "MDQ6VXNlcjQyOTM4NDA=",
                    "avatar_url": "https://avatars.githubusercontent.com/u/4293840?v=4",
                    "gravatar_id": "",
                    "url": "https://api.github.com/users/fischgeek",
                    "html_url": "https://github.com/fischgeek",
                    "followers_url": "https://api.github.com/users/fischgeek/followers",
                    "following_url": "https://api.github.com/users/fischgeek/following{/other_user}",
                    "gists_url": "https://api.github.com/users/fischgeek/gists{/gist_id}",
                    "starred_url": "https://api.github.com/users/fischgeek/starred{/owner}{/repo}",
                    "subscriptions_url": "https://api.github.com/users/fischgeek/subscriptions",
                    "organizations_url": "https://api.github.com/users/fischgeek/orgs",
                    "repos_url": "https://api.github.com/users/fischgeek/repos",
                    "events_url": "https://api.github.com/users/fischgeek/events{/privacy}",
                    "received_events_url": "https://api.github.com/users/fischgeek/received_events",
                    "type": "User",
                    "site_admin": false
                },
                "labels": [
                    {
                        "id": 505974012,
                        "node_id": "MDU6TGFiZWw1MDU5NzQwMTI=",
                        "url": "https://api.github.com/repos/Eugeny/tabby/labels/T:%20Bug",
                        "name": "T: Bug",
                        "color": "ee0701",
                        "default": false,
                        "description": null
                    }
                ],
                "state": "open",
                "locked": false,
                "assignee": null,
                "assignees": [],
                "milestone": null,
                "comments": 1,
                "created_at": "2022-08-05T16:41:14Z",
                "updated_at": "2023-10-27T07:13:21Z",
                "closed_at": null,
                "author_association": "NONE",
                "active_lock_reason": null,
                "body": "<!--\r\n# READ CAREFULLY:\r\n\r\n* **ENGLISH ONLY** - this issue tracker is English-only. Please respect the people who take time to help you with your problems.\r\n* Search existing issues first: https://github.com/Eugeny/tabby/issues\r\n* Test with the latest Tabby version: https://github.com/Eugeny/tabby/releases\r\n* Disable third-party plugins.\r\n-->\r\n\r\n**Describe the problem**:\r\nWhen using the PowerShell terminal, it auto completes the current directory shortcut (.\\\\) on every Shift+{key} stroke during a function call.\r\n\r\n**To Reproduce**:\r\nPretend you have a powershell command named `myfn` that takes 1 string parameter. \r\n1. Open the PowerShell terminal \r\n2. Type `myfn` and press space\r\n3. Pressing `shift` `\"` will trigger the (.\\\\) before your string\r\n\r\nThis is not desired because the fn only wants a string, not a path character and thus will error out. This will happen with any shift+{key} stroke during a function call.\r\n\r\nCannot figure out how to turn this off.\r\n",
                "reactions": {
                    "url": "https://api.github.com/repos/Eugeny/tabby/issues/6930/reactions",
                    "total_count": 0,
                    "+1": 0,
                    "-1": 0,
                    "laugh": 0,
                    "hooray": 0,
                    "confused": 0,
                    "heart": 0,
                    "rocket": 0,
                    "eyes": 0
                },
                "timeline_url": "https://api.github.com/repos/Eugeny/tabby/issues/6930/timeline",
                "performed_via_github_app": null,
                "state_reason": null
            },
            "comment": {
                "url": "https://api.github.com/repos/Eugeny/tabby/issues/comments/1782415034",
                "html_url": "https://github.com/Eugeny/tabby/issues/6930#issuecomment-1782415034",
                "issue_url": "https://api.github.com/repos/Eugeny/tabby/issues/6930",
                "id": 1782415034,
                "node_id": "IC_kwDOBJotwM5qPX66",
                "user": {
                    "login": "lulzhipsters",
                    "id": 14366592,
                    "node_id": "MDQ6VXNlcjE0MzY2NTky",
                    "avatar_url": "https://avatars.githubusercontent.com/u/14366592?v=4",
                    "gravatar_id": "",
                    "url": "https://api.github.com/users/lulzhipsters",
                    "html_url": "https://github.com/lulzhipsters",
                    "followers_url": "https://api.github.com/users/lulzhipsters/followers",
                    "following_url": "https://api.github.com/users/lulzhipsters/following{/other_user}",
                    "gists_url": "https://api.github.com/users/lulzhipsters/gists{/gist_id}",
                    "starred_url": "https://api.github.com/users/lulzhipsters/starred{/owner}{/repo}",
                    "subscriptions_url": "https://api.github.com/users/lulzhipsters/subscriptions",
                    "organizations_url": "https://api.github.com/users/lulzhipsters/orgs",
                    "repos_url": "https://api.github.com/users/lulzhipsters/repos",
                    "events_url": "https://api.github.com/users/lulzhipsters/events{/privacy}",
                    "received_events_url": "https://api.github.com/users/lulzhipsters/received_events",
                    "type": "User",
                    "site_admin": false
                },
                "created_at": "2023-10-27T07:13:21Z",
                "updated_at": "2023-10-27T07:13:21Z",
                "author_association": "NONE",
                "body": "I was about to raise this separately, but I think it's related.\r\n\r\nI get the same behavior, but also noticed it when doing `Shift` + `u` in which case I get the following: \r\n![image](https://github.com/Eugeny/tabby/assets/14366592/d281117e-ce96-44ce-b30c-a1c793a4537f)\r\n\r\nIf however I do `Shift` + `d` (where there are files starting with \"d\" in the current directory) I get this:\r\n![image](https://github.com/Eugeny/tabby/assets/14366592/d26fc2ad-111a-4cdd-9c44-6ee70590ca19)\r\n\r\nI too am unable to find how to change or disable this. It doesn't appear to be configurable through shortcuts, or enabled by any of the plugins\r\n",
                "reactions": {
                    "url": "https://api.github.com/repos/Eugeny/tabby/issues/comments/1782415034/reactions",
                    "total_count": 0,
                    "+1": 0,
                    "-1": 0,
                    "laugh": 0,
                    "hooray": 0,
                    "confused": 0,
                    "heart": 0,
                    "rocket": 0,
                    "eyes": 0
                },
                "performed_via_github_app": null
            }
        },
        "public": true,
        "created_at": "2023-10-27T07:13:21Z"
    },
    {
        "id": "32890299945",
        "type": "WatchEvent",
        "actor": {
            "id": 23397515,
            "login": "Falonie",
            "display_login": "Falonie",
            "gravatar_id": "",
            "url": "https://api.github.com/users/Falonie",
            "avatar_url": "https://avatars.githubusercontent.com/u/23397515?"
        },
        "repo": {
            "id": 77213120,
            "name": "Eugeny/tabby",
            "url": "https://api.github.com/repos/Eugeny/tabby"
        },
        "payload": {
            "action": "started"
        },
        "public": true,
        "created_at": "2023-10-27T06:56:11Z"
    },
    {
        "id": "32889989952",
        "type": "WatchEvent",
        "actor": {
            "id": 12878278,
            "login": "pan1560",
            "display_login": "pan1560",
            "gravatar_id": "",
            "url": "https://api.github.com/users/pan1560",
            "avatar_url": "https://avatars.githubusercontent.com/u/12878278?"
        },
        "repo": {
            "id": 77213120,
            "name": "Eugeny/tabby",
            "url": "https://api.github.com/repos/Eugeny/tabby"
        },
        "payload": {
            "action": "started"
        },
        "public": true,
        "created_at": "2023-10-27T06:40:43Z"
    },
    {
        "id": "32889709243",
        "type": "WatchEvent",
        "actor": {
            "id": 20945526,
            "login": "zkygithub",
            "display_login": "zkygithub",
            "gravatar_id": "",
            "url": "https://api.github.com/users/zkygithub",
            "avatar_url": "https://avatars.githubusercontent.com/u/20945526?"
        },
        "repo": {
            "id": 77213120,
            "name": "Eugeny/tabby",
            "url": "https://api.github.com/repos/Eugeny/tabby"
        },
        "payload": {
            "action": "started"
        },
        "public": true,
        "created_at": "2023-10-27T06:25:56Z"
    },
    {
        "id": "32889634967",
        "type": "WatchEvent",
        "actor": {
            "id": 29043573,
            "login": "Walofz",
            "display_login": "Walofz",
            "gravatar_id": "",
            "url": "https://api.github.com/users/Walofz",
            "avatar_url": "https://avatars.githubusercontent.com/u/29043573?"
        },
        "repo": {
            "id": 77213120,
            "name": "Eugeny/tabby",
            "url": "https://api.github.com/repos/Eugeny/tabby"
        },
        "payload": {
            "action": "started"
        },
        "public": true,
        "created_at": "2023-10-27T06:21:57Z"
    },
    {
        "id": "32888259080",
        "type": "WatchEvent",
        "actor": {
            "id": 40198238,
            "login": "Eddy-yun",
            "display_login": "Eddy-yun",
            "gravatar_id": "",
            "url": "https://api.github.com/users/Eddy-yun",
            "avatar_url": "https://avatars.githubusercontent.com/u/40198238?"
        },
        "repo": {
            "id": 77213120,
            "name": "Eugeny/tabby",
            "url": "https://api.github.com/repos/Eugeny/tabby"
        },
        "payload": {
            "action": "started"
        },
        "public": true,
        "created_at": "2023-10-27T04:52:54Z"
    },
    {
        "id": "32888139140",
        "type": "WatchEvent",
        "actor": {
            "id": 92195051,
            "login": "uyevan",
            "display_login": "uyevan",
            "gravatar_id": "",
            "url": "https://api.github.com/users/uyevan",
            "avatar_url": "https://avatars.githubusercontent.com/u/92195051?"
        },
        "repo": {
            "id": 77213120,
            "name": "Eugeny/tabby",
            "url": "https://api.github.com/repos/Eugeny/tabby"
        },
        "payload": {
            "action": "started"
        },
        "public": true,
        "created_at": "2023-10-27T04:43:30Z"
    },
    {
        "id": "32887222908",
        "type": "WatchEvent",
        "actor": {
            "id": 28913635,
            "login": "xiaohailimao",
            "display_login": "xiaohailimao",
            "gravatar_id": "",
            "url": "https://api.github.com/users/xiaohailimao",
            "avatar_url": "https://avatars.githubusercontent.com/u/28913635?"
        },
        "repo": {
            "id": 77213120,
            "name": "Eugeny/tabby",
            "url": "https://api.github.com/repos/Eugeny/tabby"
        },
        "payload": {
            "action": "started"
        },
        "public": true,
        "created_at": "2023-10-27T03:28:41Z"
    },
    {
        "id": "32886874289",
        "type": "WatchEvent",
        "actor": {
            "id": 100227883,
            "login": "ignorantyoung",
            "display_login": "ignorantyoung",
            "gravatar_id": "",
            "url": "https://api.github.com/users/ignorantyoung",
            "avatar_url": "https://avatars.githubusercontent.com/u/100227883?"
        },
        "repo": {
            "id": 77213120,
            "name": "Eugeny/tabby",
            "url": "https://api.github.com/repos/Eugeny/tabby"
        },
        "payload": {
            "action": "started"
        },
        "public": true,
        "created_at": "2023-10-27T03:00:51Z"
    },
    {
        "id": "32886215863",
        "type": "WatchEvent",
        "actor": {
            "id": 67535305,
            "login": "dawang1024",
            "display_login": "dawang1024",
            "gravatar_id": "",
            "url": "https://api.github.com/users/dawang1024",
            "avatar_url": "https://avatars.githubusercontent.com/u/67535305?"
        },
        "repo": {
            "id": 77213120,
            "name": "Eugeny/tabby",
            "url": "https://api.github.com/repos/Eugeny/tabby"
        },
        "payload": {
            "action": "started"
        },
        "public": true,
        "created_at": "2023-10-27T02:08:24Z"
    },
    {
        "id": "32885518558",
        "type": "WatchEvent",
        "actor": {
            "id": 99313148,
            "login": "zjwhsy",
            "display_login": "zjwhsy",
            "gravatar_id": "",
            "url": "https://api.github.com/users/zjwhsy",
            "avatar_url": "https://avatars.githubusercontent.com/u/99313148?"
        },
        "repo": {
            "id": 77213120,
            "name": "Eugeny/tabby",
            "url": "https://api.github.com/repos/Eugeny/tabby"
        },
        "payload": {
            "action": "started"
        },
        "public": true,
        "created_at": "2023-10-27T01:14:53Z"
    },
    {
        "id": "32885437788",
        "type": "WatchEvent",
        "actor": {
            "id": 57102213,
            "login": "ziyi2c",
            "display_login": "ziyi2c",
            "gravatar_id": "",
            "url": "https://api.github.com/users/ziyi2c",
            "avatar_url": "https://avatars.githubusercontent.com/u/57102213?"
        },
        "repo": {
            "id": 77213120,
            "name": "Eugeny/tabby",
            "url": "https://api.github.com/repos/Eugeny/tabby"
        },
        "payload": {
            "action": "started"
        },
        "public": true,
        "created_at": "2023-10-27T01:08:38Z"
    },
    {
        "id": "32885405234",
        "type": "WatchEvent",
        "actor": {
            "id": 40814610,
            "login": "jldpikachu",
            "display_login": "jldpikachu",
            "gravatar_id": "",
            "url": "https://api.github.com/users/jldpikachu",
            "avatar_url": "https://avatars.githubusercontent.com/u/40814610?"
        },
        "repo": {
            "id": 77213120,
            "name": "Eugeny/tabby",
            "url": "https://api.github.com/repos/Eugeny/tabby"
        },
        "payload": {
            "action": "started"
        },
        "public": true,
        "created_at": "2023-10-27T01:05:59Z"
    },
    {
        "id": "32885116896",
        "type": "IssuesEvent",
        "actor": {
            "id": 11517588,
            "login": "zhu260824",
            "display_login": "zhu260824",
            "gravatar_id": "",
            "url": "https://api.github.com/users/zhu260824",
            "avatar_url": "https://avatars.githubusercontent.com/u/11517588?"
        },
        "repo": {
            "id": 77213120,
            "name": "Eugeny/tabby",
            "url": "https://api.github.com/repos/Eugeny/tabby"
        },
        "payload": {
            "action": "opened",
            "issue": {
                "url": "https://api.github.com/repos/Eugeny/tabby/issues/9175",
                "repository_url": "https://api.github.com/repos/Eugeny/tabby",
                "labels_url": "https://api.github.com/repos/Eugeny/tabby/issues/9175/labels{/name}",
                "comments_url": "https://api.github.com/repos/Eugeny/tabby/issues/9175/comments",
                "events_url": "https://api.github.com/repos/Eugeny/tabby/issues/9175/events",
                "html_url": "https://github.com/Eugeny/tabby/issues/9175",
                "id": 1964574535,
                "node_id": "I_kwDOBJotwM51GQdH",
                "number": 9175,
                "title": "\u6bcf\u6b21\u6253\u5f00\u8f6f\u4ef6\u90fd\u4f1a\u5f39\u51fa\u4e00\u4e2a\u65b0\u7684CMD\u7a97\u53e3\uff0c\u4f46\u662f\u7a97\u53e3\u5217\u8868\u91cc\u9762\u5df2\u7ecf\u6709\u4e00\u4e2aCMD\u7a97\u53e3\u4e86\uff01",
                "user": {
                    "login": "zhu260824",
                    "id": 11517588,
                    "node_id": "MDQ6VXNlcjExNTE3NTg4",
                    "avatar_url": "https://avatars.githubusercontent.com/u/11517588?v=4",
                    "gravatar_id": "",
                    "url": "https://api.github.com/users/zhu260824",
                    "html_url": "https://github.com/zhu260824",
                    "followers_url": "https://api.github.com/users/zhu260824/followers",
                    "following_url": "https://api.github.com/users/zhu260824/following{/other_user}",
                    "gists_url": "https://api.github.com/users/zhu260824/gists{/gist_id}",
                    "starred_url": "https://api.github.com/users/zhu260824/starred{/owner}{/repo}",
                    "subscriptions_url": "https://api.github.com/users/zhu260824/subscriptions",
                    "organizations_url": "https://api.github.com/users/zhu260824/orgs",
                    "repos_url": "https://api.github.com/users/zhu260824/repos",
                    "events_url": "https://api.github.com/users/zhu260824/events{/privacy}",
                    "received_events_url": "https://api.github.com/users/zhu260824/received_events",
                    "type": "User",
                    "site_admin": false
                },
                "labels": [],
                "state": "open",
                "locked": false,
                "assignee": null,
                "assignees": [],
                "milestone": null,
                "comments": 0,
                "created_at": "2023-10-27T00:43:00Z",
                "updated_at": "2023-10-27T00:43:00Z",
                "closed_at": null,
                "author_association": "NONE",
                "active_lock_reason": null,
                "body": "Version: 1.0.201\r\nPlatform: Windows x64 10.0.22621\r\nPlugins: none\r\nFrontend: xterm-webgl\r\n\r\n",
                "reactions": {
                    "url": "https://api.github.com/repos/Eugeny/tabby/issues/9175/reactions",
                    "total_count": 0,
                    "+1": 0,
                    "-1": 0,
                    "laugh": 0,
                    "hooray": 0,
                    "confused": 0,
                    "heart": 0,
                    "rocket": 0,
                    "eyes": 0
                },
                "timeline_url": "https://api.github.com/repos/Eugeny/tabby/issues/9175/timeline",
                "performed_via_github_app": null,
                "state_reason": null
            }
        },
        "public": true,
        "created_at": "2023-10-27T00:43:01Z"
    },
    {
        "id": "32884500536",
        "type": "ForkEvent",
        "actor": {
            "id": 964538,
            "login": "Snuupy",
            "display_login": "Snuupy",
            "gravatar_id": "",
            "url": "https://api.github.com/users/Snuupy",
            "avatar_url": "https://avatars.githubusercontent.com/u/964538?"
        },
        "repo": {
            "id": 77213120,
            "name": "Eugeny/tabby",
            "url": "https://api.github.com/repos/Eugeny/tabby"
        },
        "payload": {
            "forkee": {
                "id": 710551971,
                "node_id": "R_kgDOKlopow",
                "name": "tabby",
                "full_name": "Snuupy/tabby",
                "private": false,
                "owner": {
                    "login": "Snuupy",
                    "id": 964538,
                    "node_id": "MDQ6VXNlcjk2NDUzOA==",
                    "avatar_url": "https://avatars.githubusercontent.com/u/964538?v=4",
                    "gravatar_id": "",
                    "url": "https://api.github.com/users/Snuupy",
                    "html_url": "https://github.com/Snuupy",
                    "followers_url": "https://api.github.com/users/Snuupy/followers",
                    "following_url": "https://api.github.com/users/Snuupy/following{/other_user}",
                    "gists_url": "https://api.github.com/users/Snuupy/gists{/gist_id}",
                    "starred_url": "https://api.github.com/users/Snuupy/starred{/owner}{/repo}",
                    "subscriptions_url": "https://api.github.com/users/Snuupy/subscriptions",
                    "organizations_url": "https://api.github.com/users/Snuupy/orgs",
                    "repos_url": "https://api.github.com/users/Snuupy/repos",
                    "events_url": "https://api.github.com/users/Snuupy/events{/privacy}",
                    "received_events_url": "https://api.github.com/users/Snuupy/received_events",
                    "type": "User",
                    "site_admin": false
                },
                "html_url": "https://github.com/Snuupy/tabby",
                "description": "A terminal for a more modern age",
                "fork": true,
                "url": "https://api.github.com/repos/Snuupy/tabby",
                "forks_url": "https://api.github.com/repos/Snuupy/tabby/forks",
                "keys_url": "https://api.github.com/repos/Snuupy/tabby/keys{/key_id}",
                "collaborators_url": "https://api.github.com/repos/Snuupy/tabby/collaborators{/collaborator}",
                "teams_url": "https://api.github.com/repos/Snuupy/tabby/teams",
                "hooks_url": "https://api.github.com/repos/Snuupy/tabby/hooks",
                "issue_events_url": "https://api.github.com/repos/Snuupy/tabby/issues/events{/number}",
                "events_url": "https://api.github.com/repos/Snuupy/tabby/events",
                "assignees_url": "https://api.github.com/repos/Snuupy/tabby/assignees{/user}",
                "branches_url": "https://api.github.com/repos/Snuupy/tabby/branches{/branch}",
                "tags_url": "https://api.github.com/repos/Snuupy/tabby/tags",
                "blobs_url": "https://api.github.com/repos/Snuupy/tabby/git/blobs{/sha}",
                "git_tags_url": "https://api.github.com/repos/Snuupy/tabby/git/tags{/sha}",
                "git_refs_url": "https://api.github.com/repos/Snuupy/tabby/git/refs{/sha}",
                "trees_url": "https://api.github.com/repos/Snuupy/tabby/git/trees{/sha}",
                "statuses_url": "https://api.github.com/repos/Snuupy/tabby/statuses/{sha}",
                "languages_url": "https://api.github.com/repos/Snuupy/tabby/languages",
                "stargazers_url": "https://api.github.com/repos/Snuupy/tabby/stargazers",
                "contributors_url": "https://api.github.com/repos/Snuupy/tabby/contributors",
                "subscribers_url": "https://api.github.com/repos/Snuupy/tabby/subscribers",
                "subscription_url": "https://api.github.com/repos/Snuupy/tabby/subscription",
                "commits_url": "https://api.github.com/repos/Snuupy/tabby/commits{/sha}",
                "git_commits_url": "https://api.github.com/repos/Snuupy/tabby/git/commits{/sha}",
                "comments_url": "https://api.github.com/repos/Snuupy/tabby/comments{/number}",
                "issue_comment_url": "https://api.github.com/repos/Snuupy/tabby/issues/comments{/number}",
                "contents_url": "https://api.github.com/repos/Snuupy/tabby/contents/{+path}",
                "compare_url": "https://api.github.com/repos/Snuupy/tabby/compare/{base}...{head}",
                "merges_url": "https://api.github.com/repos/Snuupy/tabby/merges",
                "archive_url": "https://api.github.com/repos/Snuupy/tabby/{archive_format}{/ref}",
                "downloads_url": "https://api.github.com/repos/Snuupy/tabby/downloads",
                "issues_url": "https://api.github.com/repos/Snuupy/tabby/issues{/number}",
                "pulls_url": "https://api.github.com/repos/Snuupy/tabby/pulls{/number}",
                "milestones_url": "https://api.github.com/repos/Snuupy/tabby/milestones{/number}",
                "notifications_url": "https://api.github.com/repos/Snuupy/tabby/notifications{?since,all,participating}",
                "labels_url": "https://api.github.com/repos/Snuupy/tabby/labels{/name}",
                "releases_url": "https://api.github.com/repos/Snuupy/tabby/releases{/id}",
                "deployments_url": "https://api.github.com/repos/Snuupy/tabby/deployments",
                "created_at": "2023-10-26T23:55:04Z",
                "updated_at": "2023-10-26T23:55:04Z",
                "pushed_at": "2023-10-26T04:36:46Z",
                "git_url": "git://github.com/Snuupy/tabby.git",
                "ssh_url": "git@github.com:Snuupy/tabby.git",
                "clone_url": "https://github.com/Snuupy/tabby.git",
                "svn_url": "https://github.com/Snuupy/tabby",
                "homepage": "https://tabby.sh",
                "size": 92659,
                "stargazers_count": 0,
                "watchers_count": 0,
                "language": null,
                "has_issues": false,
                "has_projects": true,
                "has_downloads": true,
                "has_wiki": true,
                "has_pages": false,
                "has_discussions": false,
                "forks_count": 0,
                "mirror_url": null,
                "archived": false,
                "disabled": false,
                "open_issues_count": 0,
                "license": null,
                "allow_forking": true,
                "is_template": false,
                "web_commit_signoff_required": false,
                "topics": [],
                "visibility": "public",
                "forks": 0,
                "open_issues": 0,
                "watchers": 0,
                "default_branch": "main",
                "public": true
            }
        },
        "public": true,
        "created_at": "2023-10-26T23:55:04Z"
    },
    {
        "id": "32884101442",
        "type": "WatchEvent",
        "actor": {
            "id": 47696436,
            "login": "tingv",
            "display_login": "tingv",
            "gravatar_id": "",
            "url": "https://api.github.com/users/tingv",
            "avatar_url": "https://avatars.githubusercontent.com/u/47696436?"
        },
        "repo": {
            "id": 77213120,
            "name": "Eugeny/tabby",
            "url": "https://api.github.com/repos/Eugeny/tabby"
        },
        "payload": {
            "action": "started"
        },
        "public": true,
        "created_at": "2023-10-26T23:21:29Z"
    },
    {
        "id": "32883158028",
        "type": "IssueCommentEvent",
        "actor": {
            "id": 964538,
            "login": "Snuupy",
            "display_login": "Snuupy",
            "gravatar_id": "",
            "url": "https://api.github.com/users/Snuupy",
            "avatar_url": "https://avatars.githubusercontent.com/u/964538?"
        },
        "repo": {
            "id": 77213120,
            "name": "Eugeny/tabby",
            "url": "https://api.github.com/repos/Eugeny/tabby"
        },
        "payload": {
            "action": "created",
            "issue": {
                "url": "https://api.github.com/repos/Eugeny/tabby/issues/8251",
                "repository_url": "https://api.github.com/repos/Eugeny/tabby",
                "labels_url": "https://api.github.com/repos/Eugeny/tabby/issues/8251/labels{/name}",
                "comments_url": "https://api.github.com/repos/Eugeny/tabby/issues/8251/comments",
                "events_url": "https://api.github.com/repos/Eugeny/tabby/issues/8251/events",
                "html_url": "https://github.com/Eugeny/tabby/issues/8251",
                "id": 1671570489,
                "node_id": "I_kwDOBJotwM5joiQ5",
                "number": 8251,
                "title": "The ability to disable the fading of text on unfocused terminals",
                "user": {
                    "login": "rmatte",
                    "id": 1268602,
                    "node_id": "MDQ6VXNlcjEyNjg2MDI=",
                    "avatar_url": "https://avatars.githubusercontent.com/u/1268602?v=4",
                    "gravatar_id": "",
                    "url": "https://api.github.com/users/rmatte",
                    "html_url": "https://github.com/rmatte",
                    "followers_url": "https://api.github.com/users/rmatte/followers",
                    "following_url": "https://api.github.com/users/rmatte/following{/other_user}",
                    "gists_url": "https://api.github.com/users/rmatte/gists{/gist_id}",
                    "starred_url": "https://api.github.com/users/rmatte/starred{/owner}{/repo}",
                    "subscriptions_url": "https://api.github.com/users/rmatte/subscriptions",
                    "organizations_url": "https://api.github.com/users/rmatte/orgs",
                    "repos_url": "https://api.github.com/users/rmatte/repos",
                    "events_url": "https://api.github.com/users/rmatte/events{/privacy}",
                    "received_events_url": "https://api.github.com/users/rmatte/received_events",
                    "type": "User",
                    "site_admin": false
                },
                "labels": [],
                "state": "open",
                "locked": false,
                "assignee": null,
                "assignees": [],
                "milestone": null,
                "comments": 1,
                "created_at": "2023-04-17T16:35:03Z",
                "updated_at": "2023-10-26T22:16:55Z",
                "closed_at": null,
                "author_association": "NONE",
                "active_lock_reason": null,
                "body": "**Is your feature request related to a problem? Please describe.**\r\nI find it very distracting that Tabby fades out the text in unfocused terminals. I would like to see an option to disable the fading. I already know which terminal is the active one based on how the cursor looks, this fading is unnecessary for me. Often times I need to be reading the text in the unfocused terminals and this makes it much harder on the eyes.\r\n\r\n**Describe the solution you'd like**\r\nAs an alternative you could add a thin border around the active terminal as an option instead, and also allow no fading and no border for those of us who would prefer that.\r\n\r\n**Describe alternatives you've considered**\r\nNot applicable.\r\n\r\n**Additional context**\r\nNo additonal context to add at this time.",
                "reactions": {
                    "url": "https://api.github.com/repos/Eugeny/tabby/issues/8251/reactions",
                    "total_count": 1,
                    "+1": 1,
                    "-1": 0,
                    "laugh": 0,
                    "hooray": 0,
                    "confused": 0,
                    "heart": 0,
                    "rocket": 0,
                    "eyes": 0
                },
                "timeline_url": "https://api.github.com/repos/Eugeny/tabby/issues/8251/timeline",
                "performed_via_github_app": null,
                "state_reason": null
            },
            "comment": {
                "url": "https://api.github.com/repos/Eugeny/tabby/issues/comments/1781966125",
                "html_url": "https://github.com/Eugeny/tabby/issues/8251#issuecomment-1781966125",
                "issue_url": "https://api.github.com/repos/Eugeny/tabby/issues/8251",
                "id": 1781966125,
                "node_id": "IC_kwDOBJotwM5qNqUt",
                "user": {
                    "login": "Snuupy",
                    "id": 964538,
                    "node_id": "MDQ6VXNlcjk2NDUzOA==",
                    "avatar_url": "https://avatars.githubusercontent.com/u/964538?v=4",
                    "gravatar_id": "",
                    "url": "https://api.github.com/users/Snuupy",
                    "html_url": "https://github.com/Snuupy",
                    "followers_url": "https://api.github.com/users/Snuupy/followers",
                    "following_url": "https://api.github.com/users/Snuupy/following{/other_user}",
                    "gists_url": "https://api.github.com/users/Snuupy/gists{/gist_id}",
                    "starred_url": "https://api.github.com/users/Snuupy/starred{/owner}{/repo}",
                    "subscriptions_url": "https://api.github.com/users/Snuupy/subscriptions",
                    "organizations_url": "https://api.github.com/users/Snuupy/orgs",
                    "repos_url": "https://api.github.com/users/Snuupy/repos",
                    "events_url": "https://api.github.com/users/Snuupy/events{/privacy}",
                    "received_events_url": "https://api.github.com/users/Snuupy/received_events",
                    "type": "User",
                    "site_admin": false
                },
                "created_at": "2023-10-26T22:16:55Z",
                "updated_at": "2023-10-26T22:16:55Z",
                "author_association": "NONE",
                "body": "Looks like it's hardcoded here: https://github.com/Eugeny/tabby/blob/6a458d8b9bcfbd4fafff549f9af98059aef03c85/tabby-core/src/services/themes.service.ts#L64",
                "reactions": {
                    "url": "https://api.github.com/repos/Eugeny/tabby/issues/comments/1781966125/reactions",
                    "total_count": 0,
                    "+1": 0,
                    "-1": 0,
                    "laugh": 0,
                    "hooray": 0,
                    "confused": 0,
                    "heart": 0,
                    "rocket": 0,
                    "eyes": 0
                },
                "performed_via_github_app": null
            }
        },
        "public": true,
        "created_at": "2023-10-26T22:16:56Z"
    },
    {
        "id": "32882639313",
        "type": "ForkEvent",
        "actor": {
            "id": 91288022,
            "login": "mySkillsKit",
            "display_login": "mySkillsKit",
            "gravatar_id": "",
            "url": "https://api.github.com/users/mySkillsKit",
            "avatar_url": "https://avatars.githubusercontent.com/u/91288022?"
        },
        "repo": {
            "id": 77213120,
            "name": "Eugeny/tabby",
            "url": "https://api.github.com/repos/Eugeny/tabby"
        },
        "payload": {
            "forkee": {
                "id": 710522198,
                "node_id": "R_kgDOKlm1Vg",
                "name": "tabby",
                "full_name": "mySkillsKit/tabby",
                "private": false,
                "owner": {
                    "login": "mySkillsKit",
                    "id": 91288022,
                    "node_id": "MDQ6VXNlcjkxMjg4MDIy",
                    "avatar_url": "https://avatars.githubusercontent.com/u/91288022?v=4",
                    "gravatar_id": "",
                    "url": "https://api.github.com/users/mySkillsKit",
                    "html_url": "https://github.com/mySkillsKit",
                    "followers_url": "https://api.github.com/users/mySkillsKit/followers",
                    "following_url": "https://api.github.com/users/mySkillsKit/following{/other_user}",
                    "gists_url": "https://api.github.com/users/mySkillsKit/gists{/gist_id}",
                    "starred_url": "https://api.github.com/users/mySkillsKit/starred{/owner}{/repo}",
                    "subscriptions_url": "https://api.github.com/users/mySkillsKit/subscriptions",
                    "organizations_url": "https://api.github.com/users/mySkillsKit/orgs",
                    "repos_url": "https://api.github.com/users/mySkillsKit/repos",
                    "events_url": "https://api.github.com/users/mySkillsKit/events{/privacy}",
                    "received_events_url": "https://api.github.com/users/mySkillsKit/received_events",
                    "type": "User",
                    "site_admin": false
                },
                "html_url": "https://github.com/mySkillsKit/tabby",
                "description": "A terminal for a more modern age",
                "fork": true,
                "url": "https://api.github.com/repos/mySkillsKit/tabby",
                "forks_url": "https://api.github.com/repos/mySkillsKit/tabby/forks",
                "keys_url": "https://api.github.com/repos/mySkillsKit/tabby/keys{/key_id}",
                "collaborators_url": "https://api.github.com/repos/mySkillsKit/tabby/collaborators{/collaborator}",
                "teams_url": "https://api.github.com/repos/mySkillsKit/tabby/teams",
                "hooks_url": "https://api.github.com/repos/mySkillsKit/tabby/hooks",
                "issue_events_url": "https://api.github.com/repos/mySkillsKit/tabby/issues/events{/number}",
                "events_url": "https://api.github.com/repos/mySkillsKit/tabby/events",
                "assignees_url": "https://api.github.com/repos/mySkillsKit/tabby/assignees{/user}",
                "branches_url": "https://api.github.com/repos/mySkillsKit/tabby/branches{/branch}",
                "tags_url": "https://api.github.com/repos/mySkillsKit/tabby/tags",
                "blobs_url": "https://api.github.com/repos/mySkillsKit/tabby/git/blobs{/sha}",
                "git_tags_url": "https://api.github.com/repos/mySkillsKit/tabby/git/tags{/sha}",
                "git_refs_url": "https://api.github.com/repos/mySkillsKit/tabby/git/refs{/sha}",
                "trees_url": "https://api.github.com/repos/mySkillsKit/tabby/git/trees{/sha}",
                "statuses_url": "https://api.github.com/repos/mySkillsKit/tabby/statuses/{sha}",
                "languages_url": "https://api.github.com/repos/mySkillsKit/tabby/languages",
                "stargazers_url": "https://api.github.com/repos/mySkillsKit/tabby/stargazers",
                "contributors_url": "https://api.github.com/repos/mySkillsKit/tabby/contributors",
                "subscribers_url": "https://api.github.com/repos/mySkillsKit/tabby/subscribers",
                "subscription_url": "https://api.github.com/repos/mySkillsKit/tabby/subscription",
                "commits_url": "https://api.github.com/repos/mySkillsKit/tabby/commits{/sha}",
                "git_commits_url": "https://api.github.com/repos/mySkillsKit/tabby/git/commits{/sha}",
                "comments_url": "https://api.github.com/repos/mySkillsKit/tabby/comments{/number}",
                "issue_comment_url": "https://api.github.com/repos/mySkillsKit/tabby/issues/comments{/number}",
                "contents_url": "https://api.github.com/repos/mySkillsKit/tabby/contents/{+path}",
                "compare_url": "https://api.github.com/repos/mySkillsKit/tabby/compare/{base}...{head}",
                "merges_url": "https://api.github.com/repos/mySkillsKit/tabby/merges",
                "archive_url": "https://api.github.com/repos/mySkillsKit/tabby/{archive_format}{/ref}",
                "downloads_url": "https://api.github.com/repos/mySkillsKit/tabby/downloads",
                "issues_url": "https://api.github.com/repos/mySkillsKit/tabby/issues{/number}",
                "pulls_url": "https://api.github.com/repos/mySkillsKit/tabby/pulls{/number}",
                "milestones_url": "https://api.github.com/repos/mySkillsKit/tabby/milestones{/number}",
                "notifications_url": "https://api.github.com/repos/mySkillsKit/tabby/notifications{?since,all,participating}",
                "labels_url": "https://api.github.com/repos/mySkillsKit/tabby/labels{/name}",
                "releases_url": "https://api.github.com/repos/mySkillsKit/tabby/releases{/id}",
                "deployments_url": "https://api.github.com/repos/mySkillsKit/tabby/deployments",
                "created_at": "2023-10-26T21:45:59Z",
                "updated_at": "2023-10-26T21:45:59Z",
                "pushed_at": "2023-10-26T04:36:46Z",
                "git_url": "git://github.com/mySkillsKit/tabby.git",
                "ssh_url": "git@github.com:mySkillsKit/tabby.git",
                "clone_url": "https://github.com/mySkillsKit/tabby.git",
                "svn_url": "https://github.com/mySkillsKit/tabby",
                "homepage": "https://tabby.sh",
                "size": 92659,
                "stargazers_count": 0,
                "watchers_count": 0,
                "language": null,
                "has_issues": false,
                "has_projects": true,
                "has_downloads": true,
                "has_wiki": true,
                "has_pages": false,
                "has_discussions": false,
                "forks_count": 0,
                "mirror_url": null,
                "archived": false,
                "disabled": false,
                "open_issues_count": 0,
                "license": null,
                "allow_forking": true,
                "is_template": false,
                "web_commit_signoff_required": false,
                "topics": [],
                "visibility": "public",
                "forks": 0,
                "open_issues": 0,
                "watchers": 0,
                "default_branch": "main",
                "public": true
            }
        },
        "public": true,
        "created_at": "2023-10-26T21:46:00Z"
    },
    {
        "id": "32882080462",
        "type": "WatchEvent",
        "actor": {
            "id": 24433818,
            "login": "TuzeszSzarkany",
            "display_login": "TuzeszSzarkany",
            "gravatar_id": "",
            "url": "https://api.github.com/users/TuzeszSzarkany",
            "avatar_url": "https://avatars.githubusercontent.com/u/24433818?"
        },
        "repo": {
            "id": 77213120,
            "name": "Eugeny/tabby",
            "url": "https://api.github.com/repos/Eugeny/tabby"
        },
        "payload": {
            "action": "started"
        },
        "public": true,
        "created_at": "2023-10-26T21:15:14Z"
    }
]